Workbook

Sheet 华腾2021
A1: 序号 | B1: 工程地点及内容 | C1: 单位名称 | D1: 签订日期 | E1: 合同额 | F1: 结算值 | G1: 已付款 | H1: 欠付款 | I1: 备注
A2: 21-HT-YY-OD-001 | B2: 三东小区冬季抢修 | C2: 天津天铖力帆建筑工程有限公司 | D2: 2021.4.1 | E2: 25864 | F2: 25864 | G2: 25864 | H2: =F2-G2 -> 0 | I2: 齐
A3: 21-HT-YY-OD-002 | B3: 和平村站内检修 | C3: 天津永强东成市政工程有限公司 | E3: 87020 | F3: 87020 | G3: =47020+40000 -> 87020 | H3: =F3-G3 -> 0 | I3: 齐
A4: 21-HT-YY-OD-003 | B4: 东城家园冬季检修 | C4: 天津永强东成市政工程有限公司 | E4: 46176 | F4: 46176 | G4: 46176 | H4: =F4-G4 -> 0 | I4: 齐
A5: 21-HT-YY-OD-004 | B5: 冬季内网抢修 | C5: 禹王（北京）科技工程有限公司 | D5: 2021.4.1 | E5: 255735 | F5: 255735 | G5: =45735+50000+50000+110000 -> 255735 | H5: =F5-G5 -> 0 | I5: 齐
A6: 21-HT-YY-OD-005 | B6: 百合春天 九号站冬季抢修 | C6: 天津恒鼎建筑工程有限公司 | D6: 2020.9.9 | E6: 361256 | F6: 361256 | G6: =41256+50000+40000+50000+80000+100000 -> 361256 | H6: =F6-G6 -> 0 | I6: 齐
A7: 21-HT-YY-OD-006 | B7: 万新供热2020-2021冬季运行供热管网抢修 | C7: 河北省广平县建筑安装企业集团公司 | E7: 136139 | F7: 136139 | G7: =46139+90000 -> 136139 | H7: =F7-G7 -> 0 | I7: 齐
A8: 21-HT-YY-OD-007 | B8: 海河华馨冬季抢修 | C8: 天津市信恒建筑工程有限公司 | D8: 2020.10.20 | E8: 196770 | F8: 196770 | G8: =46770+50000+80000+20000 -> 196770 | H8: =F8-G8 -> 0 | I8: 齐
A9: 21-HT-YY-OD-008 | B9: 团结北里秋丽家园冬季抢修 | C9: 天津军星管业集团建设工程有限公司 | E9: 29070 | F9: 29070 | G9: 29070 | H9: =F9-G9 -> 0 | I9: 齐
A10: 21-HT-YY-OD-009 | B10: 嘉华翠海朱庄子一村冬季抢修 | C10: 隽融建工（集团）有限公司 | E10: 90133 | F10: 90133 | G10: =45066+45067 -> 90133 | H10: =F10-G10 -> 0 | I10: 齐
A11: 21-HT-YY-OD-010 | B11: 6号站万新公寓冬季抢修 | C11: 天津市翔凯建筑安装工程有限公司 | E11: 55095 | F11: 55095 | G11: 55095 | H11: =F11-G11 -> 0 | I11: 齐
A12: 21-HT-YY-001 | B12: 2021年万新村1#2#3#换热站屋顶修缮工程 | C12: 天津大鼎市政工程有限公司 | D12: 2021.7.09 | E12: 179970 | F12: 172346 | G12: 172346 | H12: =F12-G12 -> 0 | I12: 齐
A13: 21-HT-YY-002 | B13: 2021年万新村7#8#9#换热站屋顶修缮工程 | C13: 天津大鼎市政工程有限公司 | D13: 2021.7.09 | E13: 167424 | F13: 160232 | G13: 160232 | H13: =F13-G13 -> 0 | I13: 齐
A14: 21-HT-YY-003 | B14: 2021年倚虹里1#-5#楼管道保温修缮工程 | C14: 天津大鼎市政工程有限公司 | D14: 2021.7.09 | E14: 163218 | F14: 161004 | G14: 161004 | H14: =F14-G14 -> 0 | I14: 齐
A15: 21-HT-YY-004 | B15: 2021年松风西里1#-6#楼管道保温修缮工程 | C15: 天津大鼎市政工程有限公司 | D15: 2021.7.09 | E15: 184255 | F15: 177994 | G15: =48994+49000+80000 -> 177994 | H15: =F15-G15 -> 0 | I15: 齐
A16: 21-HT-YY-005 | B16: 2021年一村换热站屋顶修缮工程 | C16: 天津大鼎市政工程有限公司 | D16: 2021.7.09 | E16: 161021 | F16: 153831 | G16: =46149+107682 -> 153831 | H16: =F16-G16 -> 0 | I16: 齐
A17: 21-HT-YY-006 | B17: 2021年和平村锅炉房手动葫芦改造工程 | C17: 天津大鼎市政工程有限公司 | D17: 2021.7.14 | E17: 124818 | F17: 115036 | G17: =45036+35000+35000 -> 115036 | H17: =F17-G17 -> 0 | I17: 齐
A18: 21-HT-YY-007 | B18: 2021年倚虹中里1#-8#楼管道保温修缮工程 | C18: 天津大鼎市政工程有限公司 | D18: 2021.7.09 | E18: 173010 | F18: 169972 | G18: =48972+121000 -> 169972 | H18: =F18-G18 -> 0 | I18: 齐
A19: 21-HT-YY-008 | B19: 2021年倚虹东里1#-5#楼管道保温修缮工程 | C19: 天津大鼎市政工程有限公司 | D19: 2021.7.09 | E19: 159886 | F19: 158558 | G19: =48558+45000+65000 -> 158558 | H19: =F19-G19 -> 0 | I19: 齐
A20: 21-HT-YY-009 | B20: 2021年万新村锅炉手动葫芦改造工程 | C20: 天津大鼎市政工程有限公司 | D20: 2021.7.14 | E20: 110949 | F20: 102255 | G20: =30676+41579+30000 -> 102255 | H20: =F20-G20 -> 0 | I20: 齐
A21: 21-HT-YY-010 | B21: 2021年松风东里1#-5#楼管道保温修缮工程 | C21: 天津大鼎市政工程有限公司 | D21: 2021.7.09 | E21: 167423 | F21: 160729 | G21: =48000+42729+70000 -> 160729 | H21: =F21-G21 -> 0 | I21: 齐
A22: 21-HT-YY-011 | B22: 2021年香兰家园换热站屋顶修缮工程 | C22: 天津大鼎市政工程有限公司 | D22: 2021.7.09 | E22: 174126 | F22: 166648 | G22: =46648+120000 -> 166648 | H22: =F22-G22 -> 0 | I22: 齐
A23: 21-HT-YY-012 | B23: 2021年百合春天换热站屋顶修缮工程 | C23: 天津大鼎市政工程有限公司 | D23: 2021.7.09 | E23: 182801 | F23: 175177 | G23: =45177+130000 -> 175177 | H23: =F23-G23 -> 0 | I23: 齐
A24: 21-HT-YY-013 | B24: 2021年沧浪西里1#2#3#入口截门更换工程 | C24: 中舰建筑工程（天津）有限公司 | D24: 2021.7.09 | E24: 116242 | F24: 108621 | G24: 108621 | H24: =F24-G24 -> 0 | I24: 齐
A25: 21-HT-YY-014 | B25: 2021年冠云中里18#-22#入口截门更换工程 | C25: 中舰建筑工程（天津）有限公司 | D25: 2021.7.09 | E25: 165605 | F25: 154987 | G25: =46496+48491+30000+30000 -> 154987 | H25: =F25-G25 -> 0 | I25: 齐
A26: 21-HT-YY-015 | B26: 2021年环秀东里19#20#21#22#入口截门更换工程 | C26: 中舰建筑工程（天津）有限公司 | D26: 2021.7.09 | E26: 149885 | F26: 140957 | G26: =42287+48670+50000 -> 140957 | H26: =F26-G26 -> 0 | I26: 齐
A27: 21-HT-YY-016 | B27: 2021年环秀西里1#2#3#4#5#入口截门更换工程 | C27: 中舰建筑工程（天津）有限公司 | D27: 2021.7.09 | E27: 150538 | F27: 140318 | G27: 140318 | H27: =F27-G27 -> 0 | I27: 齐
A28: 21-HT-YY-017 | B28: 2021年曲溪东里1#2#3#4#5#入口截门更换工程 | C28: 中舰建筑工程（天津）有限公司 | D28: 2021.7.09 | E28: 163780 | F28: 153733 | G28: =46119+47614+60000 -> 153733 | H28: =F28-G28 -> 0 | I28: 齐
A29: 21-HT-YY-018 | B29: 2021年天泉东里3#4#入口截门更换工程 | C29: 中舰建筑工程（天津）有限公司 | D29: 2021.7.09 | E29: 151117 | F29: 141768 | G29: 141768 | H29: =F29-G29 -> 0 | I29: 齐
A30: 21-HT-YY-019 | B30: 2021年秀悦换热站变压器维修项目 | C30: 中舰建筑工程（天津）有限公司 | D30: 2021.7.14 | E30: 188800 | G30: =48800+140000 -> 188800 | H30: =E30-G30 -> 0
A31: 21-HT-YY-020 | B31: 2021年天泉西里14#15#16#17#入口截门更换工程 | C31: 中舰建筑工程（天津）有限公司 | D31: 2021.7.09 | E31: 181657 | F31: 169831 | G31: 169831 | H31: =F31-G31 -> 0 | I31: 齐
A32: 21-HT-YY-021 | B32: 2021年远翠东里15#-23#入口截门更换工程 | C32: 中舰建筑工程（天津）有限公司 | D32: 2021.7.09 | E32: 190750 | F32: 177941 | G32: 177941 | H32: =F32-G32 -> 0 | I32: 齐
A33: 21-HT-YY-022 | B33: 2021年和平村供热站变压器维修项目 | C33: 中舰建筑工程（天津）有限公司 | D33: 2021.7.14 | E33: 152701 | G33: =45810+46891+60000 -> 152701 | H33: =E33-G33 -> 0 | I33: 齐
A34: 21-HT-YY-023 | B34: 2021年贵环换热站变压器维修项目 | C34: 中舰建筑工程（天津）有限公司 | D34: 2021.7.14 | E34: 133848 | G34: =40154+43694+50000 -> 133848 | H34: =E34-G34 -> 0 | I34: 找财务要了复印件
A35: 21-HT-YY-024 | B35: 2021年香兰嘉园换热站变压器维修项目 | C35: 中舰建筑工程（天津）有限公司 | D35: 2021.7.14 | E35: 136749 | G35: =46749+48000+42000 -> 136749 | H35: =E35-G35 -> 0 | I35: 齐
A36: 21-HT-YY-025 | B36: 2021华馨地热站变压器维修项目 | C36: 中舰建筑工程（天津）有限公司 | D36: 2021.7.14 | E36: 192817 | G36: =46000+46817+100000 -> 192817 | H36: =E36-G36 -> 0 | I36: 齐
A37: 21-HT-YY-026 | B37: 2021年东城家园及和平村夏季检修工程 | C37: 天津永强东成市政工程有限公司 | D37: 2021.7.22 | E37: 170458 | F37: 170458 | G37: =40458+44771+85229 -> 170458 | H37: =E37-G37 -> 0 | I37: 齐
A38: 21-HT-YY-027 | B38: 华腾招标代理咨询费/华腾供热站入围项目邀请招标 | C38: 天津津建工程造价咨询有限公司 | D38: 2021.7.02 | E38: 1291000 | G38: =45000+45000+45000+59000+150000+50000+150000+50000+100000 -> 694000 | H38: =E38-G38 -> 597000 | I38: 付款单据齐
A39: 21-HT-YY-028 | B39: 华腾供热有限责任公司各换热站变速器检测校准项目 | C39: 天津天星科技发展有限公司 | E39: 194400 | G39: =49400+45000+100000 -> 194400 | H39: =E39-G39 -> 0 | I39: 齐
A40: 21-HT-YY-029 | B40: 华腾供热有限责任公司流量计维护保养项目 | C40: 中舰建筑工程（天津）有限公司 | E40: 198856 | G40: =48856+48000+102000 -> 198856 | H40: =E40-G40 -> 0 | I40: 齐
A41: 21-HT-YY-030 | B41: 华腾供热贵环站站内夏季零星检修工程 | C41: 河北省广平县建筑安装企业集团公司 | D41: 2021.8.1 | E41: 197813 | G41: 47813 | H41: =E41-G41 -> 150000 | I41: 齐
A42: 21-HT-YY-031 | B42: 华腾供热临月里夏季零星检修工程 | C42: 河北省广平县建筑安装企业集团公司 | D42: 2021.8.1 | E42: 199772 | G42: =47813+1959+50000 -> 99772 | H42: =E42-G42 -> 100000 | I42: 齐
A43: 21-HT-YY-032 | B43: 华腾供热昆仑里、昆华里、昆悦里夏季零星检修工程 | C43: 天津荣开建筑工程有限公司 | D43: 2021.8.1 | E43: 191849 | G43: 41849 | H43: =E43-G43 -> 150000 | I43: 齐
A44: 21-HT-YY-033 | B44: 华腾供热晟悦、品香、润风、润景外网漏水检修工程 | C44: 天津荣开建筑工程有限公司 | E44: 97929 | G44: =47929+50000 -> 97929 | H44: =E44-G44 -> 0 | I44: 齐
A45: 21-HT-YY-034 | B45: 2021年华馨片区夏季维修工程 | C45: 天津市信恒建筑工程有限公司 | E45: 141372 | G45: =41372+100000 -> 141372 | H45: =E45-G45 -> 0 | I45: 齐
A46: 21-HT-YY-035 | B46: 2021年海河片区夏季检修工程 | C46: 天津市信恒建筑工程有限公司 | E46: 88420 | G46: =44210+44210 -> 88420 | H46: =E46-G46 -> 0 | I46: 齐
A47: 21-HT-YY-036 | B47: 2021万新村供热站燃气热水锅炉本体保养 | C47: 天津市辰雨达机电设备销售有限公司 | D47: 2021.7.9 | E47: 198000 | G47: =49800+48200+100000 -> 198000 | H47: =E47-G47 -> 0 | I47: 齐
A48: 21-HT-YY-037 | B48: 2021和平村供热站燃气热水锅炉本体和燃烧器维修保养 | C48: 天津市辰雨达机电设备销售有限公司 | D48: 2021.7.9 | E48: 40000 | G48: 40000 | H48: =E48-G48 -> 0 | I48: 齐
A49: 21-HT-YY-038 | B49: 2021年万新村供热站下属换热站水泵维修 | C49: 天津市西青区万润机电设备维修中心 | D49: 2021.8.2 | E49: 178000 | G49: =47800+40200+90000 -> 178000 | H49: =E49-G49 -> 0 | I49: 齐
A50: 21-HT-YY-039 | B50: 华腾地热站7月份备品备件采购项目 | C50: 天津市东丽区重信瑞能暖通设备维修中心 | D50: 2021.7.19 | E50: 116940 | G50: =46940+70000 -> 116940 | H50: =E50-G50 -> 0 | I50: 齐
A51: 21-HT-YY-040 | B51: 华腾供热站7月份备品备件采购 | C51: 天津市东丽区重信瑞能暖通设备维修中心 | D51: 2021.7.19 | E51: 41211 | G51: 41211 | H51: =E51-G51 -> 0 | I51: 齐
A52: 21-HT-YY-041 | B52: 2021和平村供热站燃气热水锅炉辅机软水器及除氧设备配件材料采购 | C52: 天津奥德宝机电设备有限公司 | D52: 2021.8.2 | E52: 71600 | G52: =35800+35800 -> 71600 | H52: =E52-G52 -> 0 | I52: 齐
A53: 21-HT-YY-042 | B53: 2021年万新村供热站燃气热水锅炉辅机软水器及除氧设备配件材料采购 | C53: 天津奥德宝机电设备有限公司 | D53: 2021.8.2 | E53: 136950 | G53: =46950+45000+45000 -> 136950 | H53: =E53-G53 -> 0 | I53: 齐
A54: 21-HT-YY-043 | B54: 2021年华腾供热站可燃气探头校准项目 | C54: 天津赛恩斯检测服务有限公司 | D54: 2021.7.21 | E54: 18020 | G54: 18020 | H54: =E54-G54 -> 0 | I54: 齐
A55: 21-HT-YY-044 | B55: 2021年品香苑地热站热泵机组维修保养项目 | C55: 中舰建筑工程（天津）有限公司 | D55: 2021.7.26 | E55: 176080 | G55: =46080+45000+85000 -> 176080 | H55: =E55-G55 -> 0 | I55: 齐
A56: 21-HT-YY-045 | B56: 2021年万新村供热站仪表拆除工程 | C56: 天津和亚建筑工程有限公司 | D56: 2021.8.2 | E56: 121926 | F56: 107720 | G56: =42316+65404 -> 107720 | H56: =F56-G56 -> 0 | I56: 齐
A57: 21-HT-YY-046 | B57: 华腾供热造价咨询服务项目 | C57: 天勤工程咨询有限公司天津分公司 | E57: 157500 | G57: =45500+45000+30000+37000 -> 157500 | H57: =E57-G57 -> 0 | I57: 齐
A58: 21-HT-YY-047 | B58: 2021年和平村供热站仪表拆除工程 | C58: 天津和亚建筑工程有限公司 | D58: 2021.8.2 | E58: 13548 | F58: 11969 | G58: 11969 | H58: =F58-G58 -> 0 | I58: 齐
A59: 21-HT-YY-048 | B59: 2021年秀悦园地热站热泵机组维修保养项目 | C59: 天津蒙兴建筑工程有限公司 | D59: 2021.7.26 | E59: 185310 | G59: =45310+48000+92000 -> 185310 | H59: =E59-G59 -> 0
A60: 21-HT-YY-049 | B60: 2021年万新村供热站锅炉燃烧器维保服务 | C60: 天津市北方建华机电设备有限公司 | D60: 2021.7.9 | E60: 198000 | G60: =49800+48200 -> 98000 | H60: =E60-G60 -> 100000 | I60: 齐
A61: 21-HT-YY-050 | B61: 2021年万新村锅炉房40吨燃气锅炉内部清垢喷防腐涂料保养 | C61: 天津市敬启建筑工程有限公司 | D61: 2021.7.27 | E61: 79200 | G61: =49200+30000 -> 79200 | H61: =E61-G61 -> 0 | I61: 齐
A62: 21-HT-YY-051 | B62: 2021年海河新天地地热泵机组维修保养项目 | C62: 天津市敬启建筑工程有限公司 | D62: 2021.7.26 | E62: 184870 | G62: =44870+46000+94000 -> 184870 | H62: =E62-G62 -> 0 | I62: 齐
A63: 21-HT-YY-052 | B63: 2021年东惠地热站热泵机组维修保养项目 | C63: 天津市敬启建筑工程有限公司 | D63: 2021.7.26 | E63: 194850 | G63: =44850+45000+105000 -> 194850 | H63: =E63-G63 -> 0 | I63: 齐
A64: 21-HT-YY-053 | B64: 2021年华馨地热站热泵机组维修保养 | C64: 天津市众致建筑工程有限公司 | D64: 2021.7.26 | E64: 150160 | G64: =45048+45112+60000 -> 150160 | H64: =E64-G64 -> 0
A65: 21-HT-YY-054 | B65: 2021年万新村锅炉房80吨燃气锅炉内部清垢喷防腐涂料保养 | C65: 天津市众致建筑工程有限公司 | D65: 2021.7.27 | E65: 158400 | G65: =48400+45000+65000 -> 158400 | H65: =E65-G65 -> 0
A66: 21-HT-YY-055 | B66: 2021年东瑞地热站热泵机组维修保养 | C66: 天津市众致建筑工程有限公司 | D66: 2021.7.24 | E66: 169260 | G66: =49260+42000+38000+40000 -> 169260 | H66: =E66-G66 -> 0 | I66: 齐
A67: 21-HT-YY-056 | B67: 华腾供热站可燃气体检测 | C67: 天津荣开建筑工程有限公司 | D67: 2021.7.29 | E67: 40897 | F67: 36343 | G67: 36343 | H67: =F67-G67 -> 0 | I67: 齐
A68: 21-HT-YY-057 | B68: 万新村供热站水泵保养 | C68: 天津市红桥区丰顺盈机电设备销售中心 | D68: 2021.7.30 | E68: 115000 | G68: =57500+57500 -> 115000 | H68: =E68-G68 -> 0 | I68: 齐
A69: 21-HT-YY-058 | B69: 华腾供热公司消防物联网DN800管线设备采购 | C69: 中安昊天（北京）安全技术有限公司 | D69: 2021.7.30 | E69: 191535 | G69: =41535+150000 -> 191535 | H69: =E69-G69 -> 0 | I69: 齐
A70: 21-HT-YY-059 | B70: 华腾供热智慧消防平台软件采购 | C70: 中安昊天（北京）安全技术有限公司 | D70: 2021.7.27 | E70: 36160 | G70: =20000+16160 -> 36160 | H70: =E70-G70 -> 0 | I70: 齐
A71: 21-HT-YY-060 | B71: 华腾供热公司DN600、DN700管线设备采购 | C71: 北京星联众合科技有限公司 | D71: 2021.7.26 | E71: 164605 | G71: =44605+120000 -> 164605 | H71: =E71-G71 -> 0 | I71: 齐
A72: 21-HT-YY-061 | B72: 华腾供热公司消防物联网DN800管线设备安装工程 | C72: 天津荣开建筑工程有限公司 | D72: 2021.7.26 | E72: 125844 | F72: 119391 | G72: =37753+81638 -> 119391 | H72: =F72-G72 -> 0 | I72: 齐
A73: 21-HT-YY-062 | B73: 和平村锅炉房燃气锅炉内部清垢喷防腐涂料保养 | C73: 天津市敬启建筑工程有限公司 | D73: 2021.7.26 | E73: 158400 | G73: =48400+48000+62000 -> 158400 | H73: =E73-G73 -> 0
A74: 21-HT-YY-063 | B74: 华腾供热站氮氧化物转换器采购 | C74: 天津仁和嘉境科技有限公司 | D74: 2021.8.12 | E74: 72000 | G74: 72000 | H74: =E74-G74 -> 0 | I74: 齐
A75: 21-HT-YY-064 | B75: 万新村供热站7号站2021年夏季维修工程 | C75: 天津恒鼎建筑工程有限公司 | D75: 2021.7.15 | E75: 155837 | F75: 168080 | G75: =40000+45837+30000+52243 -> 168080 | H75: =F75-G75 -> 0 | I75: 齐
A76: 21-HT-YY-065 | B76: 万新村供热站8号站2021年夏季维修 | C76: 天津恒鼎建筑工程有限公司 | D76: 2021.7.15 | E76: 83995 | F76: 90762 | G76: =42000+30000+18762 -> 90762 | H76: =F76-G76 -> 0 | I76: 齐
A77: 21-HT-YY-066 | B77: 万新村供热站9号站2021年夏季维修 | C77: 天津恒鼎建筑工程有限公司 | D77: 2021.7.15 | E77: 186730 | F77: 191479 | G77: =46730+144749 -> 191479 | H77: =F77-G77 -> 0 | I77: 齐
A78: 21-HT-YY-067 | B78: 万新村供热站百合春天站2021年夏季维修 | C78: 中津鹏程（天津）建筑工程有限公司 | D78: 2021.7.15 | E78: 162442 | F78: 170089 | G78: =42442+127647 -> 170089 | H78: =F78-G78 -> 0 | I78: 齐
A79: 21-HT-YY-068 | B79: 万新村供热站9号站楼道立管、盘管维修 | C79: 中津鹏程（天津）建筑工程有限公司 | D79: 2021.7.15 | E79: 145494 | F79: 154171 | G79: =45494+108677 -> 154171 | H79: =F79-G79 -> 0 | I79: 齐
A80: 21-HT-YY-069 | B80: 2021年朱庄子站检修工程 | C80: 隽融建工（集团）有限公司 | D80: 2021.8.16 | E80: 179385 | F80: 179385 | G80: =49385+30000+50000+50000 -> 179385 | H80: =E80-G80 -> 0 | I80: 齐
A81: 21-HT-YY-070 | B81: 2021年汉拿站检修工程 | C81: 隽融建工（集团）有限公司 | D81: 2021.8.16 | E81: 173698 | G81: =30000+43698+100000 -> 173698 | H81: =E81-G81 -> 0 | I81: 齐
A82: 21-HT-YY-071 | B82: 2021年一村站检修工程 | C82: 隽融建工（集团）有限公司 | D82: 2021.8.16 | E82: 190315 | G82: =40315+50000+100000 -> 190315 | H82: =E82-G82 -> 0 | I82: 齐
A83: 21-HT-YY-072 | B83: 2021年嘉华站检修工程 | C83: 隽融建工（集团）有限公司 | D83: 2021.8.18 | E83: 160703 | F83: 160703 | G83: =40703+100000+20000 -> 160703 | H83: =E83-G83 -> 0 | I83: 齐
A84: 21-HT-YY-073 | B84: 2021华腾供热电磁阀维修保养项目 | C84: 天津蒙兴建筑工程有限公司 | D84: 2021.8.6 | E84: 115154 | G84: =55154+40000+20000 -> 115154 | H84: =E84-G84 -> 0 | I84: 齐
A85: 21-HT-YY-074 | B85: 2021年万新村供热站屋面维修工程 | C85: 天津荣开建筑工程有限公司 | D85: 2021.7.26 | E85: 126748 | F85: 121550 | G85: =46748+74802 -> 121550 | H85: =F85-G85 -> 0 | I85: 齐
A86: 21-HT-YY-075 | B86: 2021年万新村锅炉房锅炉保养防腐涂料采购项目 | C86: 廊坊一萍锅炉保养工程有限公司 | D86: 2021.8.9 | E86: 197500 | G86: =47500+50000+100000 -> 197500 | H86: =E86-G86 -> 0 | I86: 齐
A87: 21-HT-YY-076 | B87: 2021年万新村供热截堵恢复材料采购 | C87: 天津市东丽区重信瑞能暖通设备维修中心 | D87: 2021.8.17 | E87: 37515.6 | G87: 37515.6 | H87: =E87-G87 -> 0 | I87: 齐
A88: 21-HT-YY-077 | B88: 2021万新村锅炉房锅炉防腐保养采购 | C88: 天津大展锅炉技术有限公司 | D88: 2021.8.9 | E88: 198500 | G88: =48500+100000+50000 -> 198500 | H88: =E88-G88 -> 0 | I88: 齐
A89: 21-HT-YY-078 | B89: 2021万新村换热站板式换热器清洗项目 | C89: 天津大展锅炉技术有限公司 | D89: 2021.8.9 | E89: 按55/平米 | F89: 339429.75 | G89: 0 | H89: =F89-G89 -> 339429.75
A90: 21-HT-YY-079 | B90: 2021万新村供热站下属369片区备品备件采购 | C90: 天津市晋之鑫五金经销部 | D90: 2021.7.21 | E90: 48460 | G90: 48460 | H90: =E90-G90 -> 0 | I90: 齐
A91: 21-HT-YY-080 | B91: 万新村供热站2021年7月份备品备件采购 | C91: 天津市津南区明悦五金经营部 | D91: 2021.7.19 | E91: 48222 | G91: 48222 | H91: =E91-G91 -> 0 | I91: 齐
A92: 21-HT-YY-081 | B92: 2021贵环站、3号站、百合站、9号站换热站等8月份备品备件采购 | C92: 天津市东丽区环昆达五金经营部 | D92: 2021.8.9 | E92: 156816.8 | G92: =46816.8+50000+50000+10000 -> 156816.8 | H92: =E92-G92 -> 0
A93: 21-HT-YY-082 | B93: 2021年一村站、东城站、好美站换热站等8月份备品备件采购 | C93: 天津市东丽区华达龙阀门销售部 | D93: 2021.8.18 | E93: 179535.1 | G93: =49535.1+20000+30000+80000 -> 179535.1 | H93: =E93-G93 -> 0 | I93: 齐
A94: 21-HT-YY-083 | B94: 2021年秋丽园北换热站离心泵采购 | C94: 天津市无双众鑫科技发展有限公司 | D94: 2021.8.13 | E94: 88340 | G94: =44170+44170 -> 88340 | H94: =E94-G94 -> 0
A95: 21-HT-YY-084 | B95: 万新村三号管理站和海山北里片区2021夏季维修工程 | C95: 禹王（北京）科技工程有限公司 | D95: 2021.7.19 | E95: 113714 | F95: 113714 | G95: =43714+30000+40000 -> 113714 | H95: =E95-G95 -> 0 | I95: 齐
A96: 21-HT-YY-085 | B96: 2021万新村供热站烟气在线监测CEMS系统维修服务 | C96: 天津市敬启建筑工程有限公司 | D96: 2021.8.20 | E96: 172840 | G96: 172840 | H96: =E96-G96 -> 0 | I96: 齐
A97: 21-HT-YY-086 | B97: 2021华腾万新村东城片区更换球阀采购 | C97: 天津市东丽区重信瑞能暖通设备维修中心 | D97: 2021.9.4 | E97: 36250 | G97: =19910+16340 -> 36250 | H97: =E97-G97 -> 0 | I97: 齐
A98: 21-HT-YY-087 | B98: 2021泰通公寓、百合春天更换阀门 | C98: 天津市东丽区重信瑞能暖通设备维修中心 | D98: 2021.9.1 | E98: 10156 | G98: =5626+4530 -> 10156 | H98: =E98-G98 -> 0 | I98: 齐
A99: 21-HT-YY-088 | B99: 2021贵环小区、卫国道十六局、机扫队、海河新天地等换热站电气材料采购 | C99: 天津鼎邦电气有限公司 | D99: 2021.9.1 | E99: 194070 | G99: =44070+150000 -> 194070 | H99: =E99-G99 -> 0 | I99: 齐
A100: 21-HT-YY-089 | B100: 2021东惠换热站电气采购 | C100: 天津鼎邦电气有限公司 | D100: 2021.9.1 | E100: 188980 | G100: =35000+48980+105000 -> 188980 | H100: =E100-G100 -> 0 | I100: 齐
...

Sheet 华腾2022
A1: 序号 | B1: 工程地点及内容 | C1: 单位名称 | D1: 签订日期 | E1: 合同额 | F1: 结算值 | G1: 已付款 | H1: 欠付款 | I1: 备注
A2: 22-HT-YY-001 | B2: 华腾供热站换热站变速器检测维修项目 | C2: 天津市昌青建筑工程有限公司 | D2: 2022.6.18 | E2: 194400 | G2: =100000+94400 -> 194400 | H2: =E2-G2 -> 0
A3: 22-HT-YY-002 | B3: 万新村1-7、9号换热站、万新公寓换热站、舒畅欣园换热站等板式换热器清洗维修 | C3: 中舰建筑工程（天津）有限公司 | D3: 2022.6.18 | E3: 101585 | G3: 101585 | H3: =E3-G3 -> 0
A4: 22-HT-YY-003 | B4: 东瑞地热站热泵机组维修保养项目 | C4: 天津市昌青建筑工程有限公司 | D4: 2022.6.13 | E4: 197320 | G4: 197320 | H4: =E4-G4 -> 0
A5: 22-HT-YY-004 | B5: 东惠地热站热泵机组维修保养项目 | C5: 天津大展建筑工程有限公司 | D5: 2022.6.13 | E5: 194815 | G5: =44815+150000 -> 194815 | H5: =E5-G5 -> 0
A6: 22-HT-YY-005 | B6: 华腾供热站流量计维护保养项目 | C6: 天津市昌青建筑工程有限公司 | D6: 2022.7.1 | E6: 198845 | G6: =100000+98845 -> 198845 | H6: =E6-G6 -> 0
A7: 22-HT-YY-006 | B7: 华腾供热站各换热站电磁阀维修保养项目 | C7: 天津大展建筑工程有限公司 | D7: 2022.6.24 | E7: 143000 | G7: =43000+100000 -> 143000 | H7: =E7-G7 -> 0
A8: 22-HT-YY-007 | B8: 万新村站（六号站、昆仑里、临月里、警苑、三石化）热量表维修 | C8: 天津久弘建筑工程有限公司 | D8: 2022.6.24 | E8: 65000 | G8: 65000 | H8: =E8-G8 -> 0
A9: 22-HT-YY-008 | B9: 华腾供热水泵维修 | C9: 天津市北辰区大力机械设备维修中心 | E9: 167500 | G9: =30000+90000+47500 -> 167500 | H9: =E9-G9 -> 0
A10: 22-HT-YY-009 | B10: 华腾供热水泵采购 | C10: 天津市红桥区丰顺盈机电设备销售中心 | E10: 65400 | G10: 65400 | H10: =E10-G10 -> 0
A11: 22-HT-YY-010 | B11: 品香苑地热站热泵机组维修保养 | C11: 正弘建业（天津）建设发展有限公司 | D11: 2022.7.8 | E11: 178740 | G11: =48740+130000 -> 178740 | H11: =E11-G11 -> 0
A12: 22-HT-YY-011 | B12: 秀悦园地热站热泵机组维修保养 | C12: 天津大鼎市政工程有限公司 | D12: 2022.6.24 | E12: 199300 | G12: 199300 | H12: =E12-G12 -> 0
A13: 22-HT-YY-012 | B13: 华馨地热站热泵机组维修 | C13: 中建贺庆（天津）建设有限公司 | D13: 2022.7.1 | E13: 155800 | G13: =45800+110000 -> 155800 | H13: =E13-G13 -> 0
A14: 22-HT-YY-013 | B14: 海河新天地地热站热泵机组维修 | C14: 中舰建筑工程（天津）有限公司 | E14: 194485 | G14: =100000+94485 -> 194485 | H14: =E14-G14 -> 0 | I14: 无合同
A15: 22-HT-YY-014 | B15: 华腾供热站水泵维修 | C15: 天津市北辰区大力机械设备维修中心 | D15: 2022.7.28 | E15: 157110 | G15: =80000+77110 -> 157110 | H15: =E15-G15 -> 0
A16: 22-HT-YY-015 | B16: 华腾供热给水工程 | C16: 天津市华源自来水工程有限公司 | D16: 2022.9.13 | E16: 192420 | G16: 192420 | H16: =E16-G16 -> 0
A17: 22-HT-YY-016 | B17: 和平村锅炉房燃气锅炉内部清垢喷防腐涂料维修保养 | C17: 天津久弘建筑工程有限公司 | E17: 70200 | G17: 70200 | H17: =E17-G17 -> 0 | I17: 无合同
A18: 22-HT-YY-017 | B18: 万新村村锅炉房燃气锅炉内部清垢喷防腐涂料维修保养 | C18: 天津云泽建筑工程有限公司 | D18: 2022.9.14 | E18: 190000 | G18: =90000+100000 -> 190000 | H18: =E18-G18 -> 0
A19: 22-HT-YY-018 | B19: 华腾供热站锅炉间改造自控系统 | C19: 天津市优硕科技有限公司 | D19: 2022.6.30 | E19: 123760 | H19: =E19-G19 -> 123760
A20: 22-HT-YY-019 | B20: 华腾供热站趸热换热间改造自控系统 | C20: 天津市擎诚科技有限公司 | D20: 2022.9.15 | E20: 194800 | H20: 194800
A21: 22-HT-YY-020 | B21: 2022-2023华腾供热冬季保驾 | C21: 天津市津东创展城市发展有限公司 | E21: =5147900.1 -> 5147900.1 | G21: =2274180.05+2873720.05 -> 5147900.1 | H21: =E21-G21 -> 0
A22: 22-HT-YY-021 | B22: 更换东康2台45kw屏蔽泵，四台季景排污泵及配套电箱 | C22: 天津市北辰区大力机械设备维修中心 | E22: 155900 | G22: 155900 | H22: =E22-G22 -> 0
A23: 22-HT-YY-022 | B23: 品香、香兰地热站提井施工 | C23: 天津海河新能源集团有限公司 | D23: 2022.10.20 | E23: 177661.28 | G23: =50000+50000+50000 -> 150000 | H23: =E23-G23 -> 27661.28
A24: 22-HT-YY-023 | C24: 取消
A25: 22-HT-YY-024 | B25: 和平村供热站彩色触摸屏采购 | C25: 天津市北方建华机电设备有限公司 | E25: 83200 | G25: 83200 | H25: =E25-G25 -> 0
A26: 22-HT-YY-025 | B26: 天津市华腾供热有限责任公司在线监测运维工作 | C26: 天津市天一生态环境科技有限公司 | D26: 2022.10.22 | E26: 360500 | G26: =100000+100000 -> 200000 | H26: =E26-G26 -> 160500
A27: 22-HT-YY-026 | B27: 华腾供热造价咨询合同 | C27: 天津市嘉华房地产开发有限责任公司 | D27: 2022.3.29 | E27: 无明细 | H27: 无明细
A28: 22-HT-YY-027 | B28: 万新村锅炉房司炉工人员安排工作 | C28: 天津恒盛嘉业科技有限公司 | D28: 2022.10.19 | E28: 700108 | G28: 100000 | H28: =E28-G28 -> 600108
A29: 22-HT-YY-028 | B29: 和平村锅炉房司炉工人员安排工作 | C29: 众投机电安装（天津）有限公司 | D29: 2022.10.19 | E29: 320492 | H29: =E29-G29 -> 320492
A30: 22-HT-YY-029 | B30: 万新村供热站、和平村供热站设备安全、正常运行服务协议 | C30: 河北工大科雅能源科技股份有限公司 | D30: 2022.11.25 | E30: 815100 | G30: =50000+100000 -> 150000 | H30: =E30-G30 -> 665100
A31: 22-HT-YY-030 | B31: 华腾、和平村供热站废气检测 | C31: 天津纳宝产品检测有限公司 | E31: 564440 | G31: =112888+112888+150000+188664 -> 564440 | H31: =E31-G31 -> 0
A32: 22-HT-YY-031 | B32: 华腾供热海河地热站、华馨地热站、嘉华地热站、中山门地热站、东康地热站压力表安全阀校准 | C32: 天津赛恩斯检测服务有限公司 | E32: 46534 | G32: 46534 | H32: =E32-G32 -> 0
A33: 22-HT-YY-032 | B33: 华腾万新村供热站下属换热站水泵维修项目 | C33: 天津市西青区万润机电设备维修中心 | E33: 46534 | G33: 46534 | H33: =E33-G33 -> 0 | I33: 无合同
A34: 22-HT-YY-033 | B34: 盛东北园锁闭阀更换 | C34: 天津鑫隆建筑工程有限公司 | E34: 52666 | G34: 52666 | H34: =E34-G34 -> 0
A35: 22-HT-YY-034 | B35: 负责品香苑、秀悦园、香兰、中山门、嘉华、东瑞、东惠、华馨、海河地热站维护值守和调试工作 | C35: 天津市津东创展城市发展有限公司 | D35: 2022.10.24 | E35: 648000 | G35: =144000+504000 -> 648000 | H35: =E35-G35 -> 0
A36: 22-HT-YY-035 | B36: 华腾供热站趸售改造工程——防爆电动调节阀采购项目 | C36: 天津凯世通阀门制造有限公司 | E36: 517150 | G36: =57150+150000+30000+80000+100000+100000 -> 517150 | H36: =E36-G36 -> 0
A37: 22-HT-YY-036 | B37: 华腾供热站趸售改造工程——板式换热器采购项目 | C37: 天津开发区大新工程技术有限公司 | D37: 2022.10.19 | E37: 1480000 | G37: =100000+150000 -> 250000 | H37: =E37-G37 -> 1230000
A38: 22-HT-YY-037 | B38: 作废 | I38: 乙方说合同作废
A39: 22-HT-YY-038 | B39: 作废 | I39: 乙方说合同作废
A40: 22-HT-YY-039 | B40: 华腾潜水泵维修及洗井项目 | C40: 天津天泰轩泓地热科技发展有限公司 | D40: 2022.5.18 | E40: 713008 | G40: =43008+150000+100000+150000+20000 -> 463008 | H40: =E40-G40 -> 250000
A41: 22-HT-YY-040 | B41: 取消
A42: 22-HT-YY-041 | B42: 2022年华腾公司自控设备材料 | C42: 天津市优硕科技有限公司 | D42: 2022.5.10 | E42: 96000 | H42: =E42-G42 -> 96000
A43: 22-HT-YY-042 | I43: 和18号合同重复 | J43: 和18号合同重复
A44: 22-HT-YY-043 | B44: 2022年夏季检修（嘉华站、一村站、翠海站、明珠站） | C44: 隽融建工（集团）有限公司 | D44: 2022.9.15 | E44: 962140 | F44: 962140 | G44: =70000+150000+150000 -> 370000 | H44: =E44-G44 -> 592140
A45: 22-HT-YY-044 | B45: 嘉悦园、万新村0号泵站购变频器 | C45: 天津鼎邦电气有限公司 | E45: 33440 | G45: 33440 | H45: =E45-G45 -> 0
A46: 22-HT-YY-045 | B46: 智慧改造华馨供热站电气控制柜 | C46: 天津鼎邦电气有限公司 | D46: 2022.10.19 | E46: 93890 | H46: =E46-G46 -> 93890
A47: 22-HT-YY-046 | B47: 华腾供热站趸售改造电气控制柜 | C47: 天津鼎邦电气有限公司 | D47: 2022.10.19 | E47: 34990 | H47: =E47-G47 -> 34990
A48: 22-HT-YY-047 | B48: 2022年停热期百合春天站检修工程 | C48: 天津恒鼎建筑工程有限公司 | D48: 2022.4.6 | E48: 262823 | F48: 262823 | G48: 100000 | H48: =E48-G48 -> 162823
A49: 22-HT-YY-048 | B49: 2022年停热期万新村9号站检修工程 | C49: 天津恒鼎建筑工程有限公司 | D49: 2022.4.9 | E49: 982245 | F49: 982245 | H49: =E49-G49 -> 982245
A50: 22-HT-YY-049 | B50: 2022年华腾供热停热期检修（贵环、昆仑里、秋丽） | C50: 天津荣开建筑工程有限公司 | D50: 2022.4.12 | E50: 987000 | F50: 987000 | G50: =50000+150000+50000+180000+170000 -> 600000 | H50: =E50-G50 -> 387000
A51: 22-HT-YY-050 | B51: 万新村供热站换热器检修 | C51: 天津开发区大新工程技术有限公司 | D51: 2022.10.25 | E51: 211167 | G51: =50000+150000+11167 -> 211167 | H51: =E51-G51 -> 0
A52: 22-HT-YY-051 | B52: 2022年停热期检修（盛东北园、程林北里） | C52: 天津鑫隆建筑工程有限公司 | D52: 2022.6.29 | E52: 234277 | F52: 234277 | G52: =50000+50000+100000 -> 200000 | H52: =F52-G52 -> 34277
A53: 22-HT-YY-052 | B53: 香邑国际换热器及板片采购 | C53: 天津市重信瑞能科技发展有限公司 | D53: 2022.12.10 | E53: 170280 | H53: =E53-G53 -> 170280
A54: 22-HT-YY-053 | B54: 购补水泵 | C54: 天津市无双众鑫科技发展有限公司 | D54: 2022.10.25 | E54: 77700 | G54: 77700 | H54: =E54-G54 -> 0
A55: 22-HT-YY-054 | B55: 华腾供热站压力表检测 | C55: 天津赛恩斯检测服务有限公司 | E55: 2120 | G55: 2120 | H55: =E55-G55 -> 0
A56: 22-HT-YY-055 | B56: 华馨地热站改造工程—热力管道工程 | C56: 天津市融辉政达建筑工程有限公司 | D56: 2022.6.14 | E56: 377351 | H56: =E56-G56 -> 377351
A57: 22-HT-YY-056 | B57: 2022年停热期东康站AB站及小区检修 | C57: 天津市融辉政达建筑工程有限公司 | D57: 2022.6.16 | E57: 665034 | F57: 665034 | G57: =100000+89002+150000+100000 -> 439002 | H57: =E57-G57 -> 226032
A58: 22-HT-YY-057 | B58: 2022年热期华馨站、海河站检修 | C58: 天津市融辉政达建筑工程有限公司 | D58: 2022.6.14 | E58: 678004 | G58: =100000+78004 -> 178004 | H58: =E58-G58 -> 500000
A59: 22-HT-YY-058 | B59: 2022年华腾供热品香园、秀悦园变频器更换项目 | C59: 天津鼎邦电气有限公司 | D59: 2022.12.12 | E59: 132625 | H59: =E59-G59 -> 132625
A60: 22-HT-YY-059 | B60: 华腾供热站管道测漏费 | C60: 久跃管道工程（天津）有限公司 | E60: 33000 | G60: 33000 | H60: =E60-G60 -> 0
A61: 22-HT-YY-060 | B61: 东康站、华馨站、嘉华站水泵、换热器及配件采购 | C61: 天津普达瑞克机电工程有限公司 | D61: 2022.12.12 | E61: 265722 | G61: =50000+150000 -> 200000 | H61: =E61-G61 -> 65722
A62: 22-HT-YY-061 | B62: 华腾万新村供热站下属换热站水泵维修项目 | C62: 天津市西青区万润机电设备维修中心 | D62: 2022.11.30 | E62: 327600 | G62: =47600+160000+120000 -> 327600 | H62: =E62-G62 -> 0
A63: 22-HT-YY-062 | B63: 2022年停热期检修（中山门地热站、舒畅嘉园） | C63: 天津军星管业集团建设工程有限公司 | D63: 2022.4.25 | E63: 50844 | G63: 40000 | H63: =E63-G63 -> 10844
A64: 22-HT-YY-063 | B64: 秀悦园水泵修理机组、电缆 | C64: 天津甘泉集团有限公司 | D64: 2022.10.25 | E64: 195800 | G64: =100000+95800 -> 195800 | H64: =E64-G64 -> 0
A65: 22-HT-YY-064 | B65: 品香苑修理机组、电缆 | C65: 天津甘泉集团有限公司 | D65: 2022.10.25 | E65: 71020 | G65: 71020 | H65: =E65-G65 -> 0
A66: 22-HT-YY-065 | B66: 香兰家园修理机组，泵管 | C66: 天津甘泉集团有限公司 | D66: 2022.10.25 | E66: 65310 | G66: 65310 | H66: =E66-G66 -> 0
A67: 22-HT-YY-066 | B67: 华腾供热2022-2023年锅炉节能防腐保养 | C67: 廊坊诺一锅炉保养有限公司 | D67: 2022.4.25 | E67: 724900 | H67: 724900
H68: =SUM(H2:H67) -> 8163540.3

Sheet 华腾2023
A1: 序号 | B1: 工程地点及内容 | C1: 单位名称 | D1: 签订日期 | E1: 合同额 | F1: 结算值 | G1: 已付款 | H1: 欠付款 | I1: 备注
A2: 23-HT-YY-001 | B2: 万新村、和平村在线监测设备维护 | C2: 天津市天一生态环境科技有限公司 | D2: 2023.1.17 | E2: 154000 | G2: =92400+61600 -> 154000 | H2: =E2-G2 -> 0
A3: 23-HT-YY-002 | B3: 万新村供热站、和平村供热站锅炉保养 | C3: 天津市辰雨达机电设备销售有限公司 | D3: 2023.1.17 | E3: 187000 | G3: =74800+112200 -> 187000 | H3: =E3-G3 -> 0
A4: 23-HT-YY-003 | B4: 东康家园抢修 | C4: 天津天泰宏凯泵业制造有限公司 | D4: 2023.2.1 | E4: 118000 | G4: 118000 | H4: =E4-G4 -> 0
A5: 23-HT-YY-004 | B5: 2022年华腾供热冬季备品备件维修材料采购 | C5: 天津市重信瑞能科技发展有限公司 | D5: 2023.1.5 | E5: 994146 | G5: =100000+100000+180000+128000 -> 508000 | H5: =E5-G5 -> 486146
A6: 23-HT-YY-005 | B6: 万新村、和平村供热站采购 | C6: 天津市北方建华机电设备有限公司 | D6: 2023.2.11 | E6: 92771 | G6: 80000 | H6: =E6-G6 -> 12771 | I6: 开票时：将维修费和采购费用分开开票
A7: 23-HT-YY-006 | B7: 华腾供热趸热购板片 | C7: 天津市津能双鹤热力设备有限公司 | D7: 2023.1.30 | E7: 648000 | G7: =180000+468000 -> 648000 | H7: =E7-G7 -> 0
A8: 23-HT-YY-007 | B8: 华腾锅炉房升级改造项目 | C8: 天津市津能双鹤热力设备有限公司 | D8: 2023.4.24 | E8: 270000 | G8: =120000+100000+50000 -> 270000 | H8: =E8-G8 -> 0
A9: 23-HT-YY-008 | B9: 海河供热站自来水及一次管网改造工程 | C9: 天津市融辉政达建筑工程有限公司 | D9: 2023.2.16 | E9: 70500 | F9: 70500 | G9: =50000+20500 -> 70500 | H9: =E9-G9 -> 0
A10: 23-HT-YY-009 | B10: 华腾地热测绘服务 | C10: 天津恒德建设工程技术有限公司 | D10: 2023.2.21 | E10: 457600 | G10: =100000+20000+50000 -> 170000 | H10: =E10-G10 -> 287600
A11: 23-HT-YY-010 | B11: 华腾供热在线监测设备数采仪更换及在线设备分析仪维修 | C11: 天津市天一生态环境科技有限公司 | D11: 2023.2.21 | E11: 316000 | G11: =100000+50000+100000 -> 250000 | H11: =E11-G11 -> 66000 | I11: 开票时：将维修费和采购费用分开开票
A12: 23-HT-YY-011 | B12: 和平村供热站管道漏水检测 | C12: 久跃管道工程（天津）有限公司 | D12: 2023.2.10 | E12: 11157 | G12: 11157 | H12: =E12-G12 -> 0
A13: 23-HT-YY-012 | B13: 购臭味剂、工业盐（第一批） | C13: 廊坊一萍锅炉保养工程有限公司 | D13: 2023.1.9 | E13: 897650 | G13: 160000 | H13: =E13-G13 -> 737650
A14: 23-HT-YY-013 | B14: 缓蚀阻垢剂（第一批) | C14: 天津大展锅炉技术有限公司 | D14: 2023.1.9 | E14: 880000 | H14: =E14-G14 -> 880000
A15: 23-HT-YY-014 | B15: 购缓蚀色精、缓蚀阻垢剂（第一批) | C15: 廊坊诺一锅炉保养有限公司 | D15: 2023.1.9 | E15: 727000 | G15: =90000+170000 -> 260000 | H15: =E15-G15 -> 467000
A16: 23-HT-YY-015 | B16: 万新村供热系统评价及供热系统运行策略指导 | C16: 天津清捷能源环境科技有限公司 | D16: 2023.2.28 | E16: 650000 | G16: =195000+195000+150000+110000 -> 650000 | H16: =E16-G16 -> 0
A17: 23-HT-YY-016 | B17: 缓蚀阻垢剂（第二批) | C17: 天津大展锅炉技术有限公司 | D17: 2023.2.28 | E17: 880000 | H17: =E17-G17 -> 880000
A18: 23-HT-YY-017 | B18: 购臭味剂、缓蚀色精（第二批） | C18: 廊坊诺一锅炉保养有限公司 | D18: 2023.2.28 | E18: 875200 | H18: =E18-G18 -> 875200
A19: 23-HT-YY-018 | B19: 板换清洗镀膜保养施工 | C19: 天津大展锅炉技术有限公司 | D19: 2023.2.28 | E19: 386295.8 | H19: =E19-G19 -> 386295.8
A20: 23-HT-YY-019 | B20: 购板式换热器、胶垫 | C20: 天津开发区大新工程技术有限公司 | D20: 2023.2.27 | E20: 72104 | H20: =E20-G20 -> 72104
A21: 23-HT-YY-020 | B21: 板式换热器维修 | C21: 天津开发区大新工程技术有限公司 | D21: 2023.2.28 | E21: 136700 | G21: 136700 | H21: =E21-G21 -> 0
A22: 23-HT-YY-021 | B22: 华腾供热公司趸热隔压换热站改造工程 | C22: 天津市政工程设计研究总院有限公司 | D22: 2023.2.13 | E22: 192000 | G22: 50000 | H22: =E22-G22 -> 142000
A23: 23-HT-YY-022 | B23: 购缓蚀阻垢剂（第三批） | C23: 天津大展锅炉技术有限公司 | D23: 2023.3.6 | E23: 440000 | G23: =176000+150000 -> 326000 | H23: =E23-G23 -> 114000
A24: 23-HT-YY-023 | B24: 购臭味剂 | C24: 廊坊一萍锅炉保养工程有限公司 | D24: 2023.3.3 | E24: 403200 | H24: =E24-G24 -> 403200
A25: 23-HT-YY-024 | B25: 购臭味剂、工业盐（第二批） | C25: 廊坊一萍锅炉保养工程有限公司 | D25: 2023.2.27 | E25: 847250 | H25: =E25-G25 -> 847250
A26: 23-HT-YY-025 | B26: 华腾供热管道检测 | C26: 久跃管道工程（天津）有限公司 | D26: 2023.2.28 | E26: 36000 | G26: 36000 | H26: =E26-G26 -> 0
A27: 23-HT-YY-026 | B27: 购缓蚀色精（第三批） | C27: 廊坊诺一锅炉保养有限公司 | D27: 2023.3.1 | E27: 743600 | H27: =E27-G27 -> 743600
A28: 23-HT-YY-027 | B28: 万新村供热站板换清洗抢修 | C28: 天津大展建筑工程有限公司 | D28: 2023.1.18 | E28: 135460 | G28: 135460 | H28: =E28-G28 -> 0
A29: 23-HT-YY-028 | B29: 华腾供热地热供热站清洗抢修 | C29: 天津市昌青建筑工程有限公司 | D29: 2023.1.18 | E29: 170358 | G29: 170358 | H29: =E29-G29 -> 0
A30: 23-HT-YY-029 | B30: 华腾供热四号站换热器更换项目 | C30: 天津普达瑞克机电工程有限公司 | D30: 2023.3.13 | E30: 215892 | H30: =E30-G30 -> 215892
A31: 23-HT-YY-030 | B31: 2023年1月份维修材料采购 | C31: 天津普达瑞克机电工程有限公司 | D31: 2023.4.3 | E31: 402106 | H31: =E31-G31 -> 402106
A32: 23-HT-YY-031 | B32: 香邑国际18号楼门前、远洋食堂外人行便道给定范围内物探 | C32: 天津海滨工程勘察设计有限公司 | D32: 2023.4.3 | E32: 15800 | G32: 15800 | H32: =E32-G32 -> 0
A33: 23-HT-YY-032 | B33: 2023年造价咨询合同框架协议 | C33: 天津宸颍工程咨询有限公司 | D33: 2023.2.10 | E33: 框架协议 | F33: =120082-1700+21452 -> 139834 | G33: =29411+51467 -> 80878 | H33: =F33-G33 -> 58956
A34: 23-HT-YY-033 | B34: 华腾供热站内燃气管道维护 | C34: 程然（天津）建设集团有限公司 | D34: 2023.4.19 | E34: 195000 | G34: =30000+165000 -> 195000 | H34: =E34-G34 -> 0
A35: 23-HT-YY-034 | B35: 华腾供热4号站蝶式止回阀采购项目 | C35: 天津市塘沽塘阀阀门有限公司 | D35: 2023.3.22 | E35: 5730 | G35: 5730 | H35: =E35-G35 -> 0
A36: 23-HT-YY-035 | B36: 孵化园咨询服务 | C36: 天津清捷能源环境科技有限公司 | D36: 2023.4.20 | E36: 50000 | G36: 20000 | H36: =E36-G36 -> 30000
A37: 23-HT-YY-036 | B37: 2023年度华腾供热招标代理服务 | C37: 天津市泛亚工程咨询有限公司 | D37: 2023.4.7 | E37: 无明细 | H37: 无明细
A38: 23-HT-YY-037 | B38: 2023年度华腾供热招标代理服务 | C38: 天津宸颖工程咨询有限公司 | D38: 2023.4.7 | E38: 无明细 | H38: 无明细
A39: 23-HT-YY-038 | B39: 2023年度华腾供热招标代理服务 | C39: 天津津运工程咨询有限公司 | D39: 2023.4.7 | E39: 无明细 | H39: 无明细
A40: 23-HT-YY-039 | B40: 2023年度华腾供热招标代理服务 | C40: 中大国信工程管理有限公司 | D40: 2023.5.25 | E40: 无明细 | H40: 无明细
A41: 23-HT-YY-040 | B41: 华腾万新村供热站下属换热站水泵维修项目 | C41: 天津市北辰区大力机械设备维修中心 | D41: 2023.2.18 | E41: 177000 | G41: =100000+77000 -> 177000 | H41: =E41-G41 -> 0
A42: 23-HT-YY-041 | B42: 建设工程监理框架合同 | C42: 天津海通工程管理有限公司 | D42: 2023.5.7 | E42: 无明细 | H42: 无明细
A43: 23-HT-YY-042 | B43: 建设工程招标代理框架协议 | C43: 天津市泛亚工程咨询有限公司 | D43: 2023.4.28 | E43: 无明细 | H43: 无明细
A44: 23-HT-YY-043 | B44: 华腾供热2023年锅炉喷涂防腐保养、水侧疏通 | C44: 廊坊诺一锅炉保养有限公司 | D44: 2023.7.28 | E44: 1759040 | H44: =E44-G44 -> 1759040
A45: 23-HT-YY-044 | B45: 管道漏水监测施工 | C45: 久跃管道工程（天津）有限公司 | D45: 2023.7.28 | E45: 无明细 | F45: =16000+92000+68000+68000+88000 -> 332000 | G45: =100000+72000+50000+110000 -> 332000 | H45: =F45-G45 -> 0
A46: 23-HT-YY-045 | B46: 百合春天、9号站2023年夏季维修 | C46: 天津恒鼎建筑工程有限公司 | D46: 2023.7.28 | E46: 造价金额*0.94 | F46: 1985769 | G46: 50000 | H46: =F46-G46 -> 1935769
A47: 23-HT-YY-046 | B47: 海河新天地、华馨地热站、东康地热站等2023年夏季维修 | C47: 天津天铖力帆建筑工程有限公司 | D47: 2023.7.28 | E47: 造价金额*0.92 | F47: 1349842 | G47: =100000+100000+149842 -> 349842 | H47: =F47-G47 -> 1000000
A48: 23-HT-YY-047 | B48: 华腾供热六号站、香兰家园等供热站2023年夏季维修 | C48: 慧通力达集团有限公司 | D48: 2023.7.28 | E48: 造价金额*0.94 | F48: 2481165 | G48: =100000+50000+50000+100000 -> 300000 | H48: =F48-G48 -> 2181165
A49: 23-HT-YY-048 | B49: 一村、明珠、嘉华新苑地热站等2023年夏季维修 | C49: 隽融建工（集团）有限公司 | D49: 2023.7.28 | E49: 造价金额*0.92 | F49: 2006606 | H49: =F49-G49 -> 2006606
A50: 23-HT-YY-049 | B50: 三号站、万新公寓、海山站2023年夏季维修 | C50: 禹王（北京）科技工程有限公司 | D50: 2023.7.28 | E50: 造价金额*0.92 | F50: 2432304 | G50: =150000+700000 -> 850000 | H50: =F50-G50 -> 1582304 | I50: 债权转让给河南磊升建筑工程有限公司河东分公司
A51: 23-HT-YY-050 | B51: 贵环站、昆仑里站、秋丽站等供热站2023年夏季维修 | C51: 天津荣开建筑工程有限公司 | D51: 2023.7.28 | E51: 造价金额*0.92 | F51: 1792383 | H51: =F51-G51 -> 1792383
A52: 23-HT-YY-051 | B52: 东城供热站2023年夏季维修 | C52: 天津永强东成市政工程有限公司 | D52: 2023.7.28 | E52: 造价金额*0.94 | F52: 800902 | G52: =150000+190902 -> 340902 | H52: =F52-G52 -> 460000
A53: 23-HT-YY-052 | B53: 2023年应急检查维护维修 | C53: 天津诚泓建筑工程有限公司 | D53: 2023.7.26 | E53: 70745 | G53: =30000+40745 -> 70745 | H53: =E53-G53 -> 0
A54: 23-HT-YY-053 | B54: 万新村供热站锅炉系统维护及有关设备维护保养 | C54: 天津市北方建华机电设备有限公司 | D54: 2023.7.18 | E54: 665000 | G54: 100000 | H54: =E54-G54 -> 565000
A55: 23-HT-YY-054 | B55: 万新村二级泵及十六局箱式换热站设备采购 | C55: 上海凯泉泵业（集团）有限公司 | D55: 2023.8.16 | E55: 2662000 | G55: =798600+150000+150000+100000+50000+700000 -> 1948600 | H55: =E55-G55 -> 713400
A56: 23-HT-YY-055 | B56: 换热站改造项目及新建项目设计服务 | C56: 中科瑞城设计有限公司 | D56: 2023.9 | E56: 无明细（见71号合同） | H56: 无明细（见71号合同）
A57: 23-HT-YY-056 | B57: 2023年华腾供热碎修工程（第一批） | C57: 天津源融市政工程有限公司 | D57: 2023.8.20 | E57: 95034 | G57: =50000+45034 -> 95034 | H57: =E57-G57 -> 0
A58: 23-HT-YY-057 | B58: 万新村锅炉房改造方案设计 | C58: 中国市政工程华北设计研究总院有限公司 | D58: 2023.8.25 | E58: 181000 | H58: =E58-G58 -> 181000
A59: 23-HT-YY-058 | B59: 万新村供热站消防改造工程 | C59: 天津利安信合科技发展有限公司 | D59: 2023.10.28 | E59: 30677.36 | H59: =E59-G59 -> 30677.36
A60: 23-HT-YY-059 | B60: 万新村供热站下属2号站拆分工程—室外管网工程 | C60: 天津市祥宜建筑安装有限公司 | D60: 2023.8.30 | E60: 453368 | F60: 453368 | G60: =100000+113368 -> 213368 | H60: =E60-G60 -> 240000
A61: 23-HT-YY-060 | B61: 2023年华腾供热地热潜水泵维修项目 | C61: 天津天泰轩泓地热科技发展有限公司 | D61: 2023.9.30 | E61: 394465 | G61: 100000 | H61: =E61-G61 -> 294465
A62: 23-HT-YY-061 | B62: 华腾供热万新村1-9号站二网循环泵采购及服务项目 | C62: 天津市无双众鑫科技发展有限公司 | D62: 2023.9.7 | E62: 814300 | G62: =100000+195000+150000 -> 445000 | H62: =E62-G62 -> 369300
A63: 23-HT-YY-062 | B63: 2023年盛东北园、程林北里夏季检修项目 | C63: 天津鑫隆建筑工程有限公司 | D63: 2023.9.24 | E63: 113433 | H63: =E63-G63 -> 113433
A64: 23-HT-YY-063 | B64: 秀悦站耐高温潜水电泵 | C64: 天津天泰宏凯泵业制造有限公司 | D64: 2023.9.8 | E64: 76000 | G64: 76000 | H64: =E64-G64 -> 0
A65: 23-HT-YY-064 | B65: 华腾供热品香、香兰地热井潜水泵项目 | C65: 天津天泰轩泓地热科技发展有限公司 | D65: 2023.9.8 | E65: 197000 | G65: 197000 | H65: =E65-G65 -> 0
A66: 23-HT-YY-065 | B66: 2023年华腾供热贵环小区、汇海南里、汇海北里二级泵采购项目 | C66: 上海凯泉泵业（集团）有限公司 | D66: 2023.9.16 | E66: 92505 | G66: 92505 | H66: =E66-G66 -> 0
A67: 23-HT-YY-066 | B67: 2023年万新村下属换热站备用二级泵采购项目 | C67: 上海凯泉泵业（集团）有限公司 | E67: 60462 | G67: 60462 | H67: =E67-G67 -> 0
A68: 23-HT-YY-067 | B68: 万新村供热站下属聚醚部厂区院内供暖泵站设施迁移改造项目-电气工程 | C68: 天津鼎邦电气有限公司 | D68: 2023.9.13 | E68: 71850 | H68: =E68-G68 -> 71850
A69: 23-HT-YY-068 | B69: 华腾供热万新村1-9号站二网循环泵配套变频柜采购及服务项目 | C69: 天津鼎邦电气有限公司 | D69: 2023.9.13 | E69: 403210 | H69: =E69-G69 -> 403210
A70: 23-HT-YY-069 | B70: 2023年华腾供热VPN网络监控安装及其他网络维修 | C70: 中国联合网络通信有限公司天津市分公司 | D70: 2023.9.12 | E70: 52743 | F70: 52743 | G70: 52743 | H70: =E70-G70 -> 0
A71: 23-HT-YY-070 | B71: 天津市河东区中山门地热尾水梯级利用项目 | C71: 中国建筑科学研究院天津分院 | D71: 2023.9.6 | E71: 30000 | H71: =E71-G71 -> 30000
A72: 23-HT-YY-071 | B72: 万新村2号站拆分工程、于明庄二次网及楼道立管改造工程、远翠东里9# 10#楼前管改造工程 | C72: 中科瑞城设计有限公司 | D72: 2023.10.16 | E72: 105400 | G72: =50000+55400 -> 105400 | H72: =E72-G72 -> 0
A73: 23-HT-YY-072 | B73: 华腾供热2023年度能源管家咨询服务项目 | C73: 天津艾菲克科技有限公司 | D73: 2023.9.22 | E73: 30000 | G73: 30000 | H73: =E73-G73 -> 0
A74: 23-HT-YY-073 | B74: 华腾万新村供热站下属换热站水泵维修项目 | C74: 天津市北辰区大力机械设备维修中心 | D74: 2023.10.10 | E74: 78900 | G74: 78900 | H74: =E74-G74 -> 0
A75: 23-HT-YY-074 | B75: 华腾供热可燃气体报警系统采购及安装 | C75: 天津市益高燃气设备科技有限公司 | D75: 2023.10.17 | E75: 26215 | G75: 26215 | H75: =E75-G75 -> 0
A76: 23-HT-YY-075 | B76: 华腾供热电磁流量计 | C76: 天津市大港仪表有限公司 | D76: 2023.10.12 | E76: 13000 | G76: 13000 | H76: =E76-G76 -> 0
A77: 23-HT-YY-076 | B77: 华腾供热供热系统维护（抢修）协议 | C77: 天津市津东创展城市发展有限公司 | D77: 2023.10.13 | E77: 5110679.6 | F77: 5110679.6 | G77: =2032193+2056350.68+1022135.92 -> 5110679.6 | H77: =E77-G77 -> 0 | I77: 津东创展所有人员明细表都放在此合同里
A78: 23-HT-YY-077 | B78: 华腾供热地热站维护（值守）和调试协议 | C78: 天津市津东创展城市发展有限公司 | D78: 2023.10.13 | E78: 648000 | G78: =259200+259200+129600 -> 648000 | H78: =E78-G78 -> 0
A79: 23-HT-YY-078 | B79: 华腾供热万新村二级泵及下属换热站变频柜改造服务项目 | C79: 天津市东和瑞捷科技发展有限公司 | D79: 2023.10.26 | E79: 2693250 | G79: =807975+100000+100000+95000 -> 1102975 | H79: =E79-G79 -> 1590275
A80: 23-HT-YY-079 | B80: 华腾供热万新村11、15、16、17区热力管线探测服务项目 | C80: 天津海滨工程勘察设计有限公司 | D80: 2023.10.17 | E80: 90000 | G80: =45000+45000 -> 90000 | H80: =E80-G80 -> 0
A81: 23-HT-YY-080 | B81: 华腾供热中山门地热尾水梯级利用测绘服务项目 | C81: 天津海滨工程勘察设计有限公司 | D81: 2023.10.17 | E81: 30000 | G81: 30000 | H81: =E81-G81 -> 0
A82: 23-HT-YY-081 | B82: 华腾供热下属换热站运行水泵检查维护保养项目 | C82: 天津市西青区万润机电设备维修中心 | D82: 2023.9.22 | E82: 166370 | G82: =40000+126370 -> 166370 | H82: =E82-G82 -> 0
A83: 23-HT-YY-082 | B83: 万新村、和平村燃气锅炉房供热冬季运行、电工值守及问题处理 | C83: 天津市津东创展城市发展有限公司 | D83: 2023.10.13 | E83: =2686000+129100 -> 2815100 | G83: =792300+798100+1095600 -> 2686000 | H83: =E83-G83 -> 129100 | I83: 运行服务1334000 电工值守 972000 问题处理 380000
A84: 23-HT-YY-083 | B84: 华腾供热网络调测升级及服务 | C84: 中国联合网络通信有限公司天津市分公司 | D84: 2023.10.25 | E84: 77000 | G84: 77000 | H84: =E84-G84 -> 0
A85: 23-HT-YY-084 | B85: 华腾供热19处站点电力设备维修工程 | C85: 天津开发区君安电气有限公司 | D85: 2023.10.30 | E85: 1900107 | F85: 1991682 | G85: =190010.7+100000+180000+173188.2+100000+100000+160000 -> 1003198.9 | H85: =F85-G85 -> 988483.1
A86: 23-HT-YY-085 | B86: 和平村供热站锅炉系统维护及设备维护保养 | C86: 天津市辰雨达机电设备销售有限公司 | D86: 2023.9.19 | E86: 63000 | H86: =E86-G86 -> 63000
A87: 23-HT-YY-086 | B87: 华腾供热2023-2024万新村供热站能源管理项目 | C87: 北京智联科电技术有限公司 | D87: 2023.11.7 | E87: 无明细 | F87: =32780.8+45427.2+36192+43368 -> 157768 | G87: =32780.8+81619.2+43368 -> 157768 | H87: =F87-G87 -> 0
A88: 23-HT-YY-087 | B88: 河东区华腾供热调度运行技术服务项目 | C88: 天津市东和瑞捷科技发展有限公司 | D88: 2023.10.19 | E88: 480000 | G88: =192000+100000+188000 -> 480000 | H88: =E88-G88 -> 0
A89: 23-HT-YY-088 | B89: 2023年万新站及海河新天地地热站10kv变电站运维 | C89: 天津民安电力设备有限公司 | D89: 2023.10 | E89: 180000 | G89: =45000+30000+50000 -> 125000 | H89: =E89-G89 -> 55000
A90: 23-HT-YY-089 | B90: 华腾供热2023-2024供热季环境监测项目 | C90: 天津纳宝产品检测有限公司 | D90: 2023.11.17 | E90: 588954 | G90: =117790.8+117790.8+117790.8+117790.8+117790.8 -> 588954 | H90: =E90-G90 -> 0
A91: 23-HT-YY-090 | B91: 2023年和平村夏季检修 | C91: 天津景润鸿诚市政工程有限公司 | D91: 2023.10.26 | E91: 189945 | G91: 189945 | H91: =E91-G91 -> 0
A92: 23-HT-YY-091 | B92: 2023万新站一网蝶阀采购项目 | C92: 天津凯世通阀门制造有限公司 | D92: 2023.11.16 | E92: 538900 | G92: =100000+150000+150000 -> 400000 | H92: =E92-G92 -> 138900
A93: 23-HT-YY-092 | B93: 华腾供热所属供热站锅炉房公用部分计算机控制系统技术服务项目 | C93: 天津市优硕科技有限公司 | D93: 2023.11.6 | E93: 40000 | H93: =E93-G93 -> 40000
A94: 23-HT-YY-093 | B94: 中山门地热尾水梯级利用—设计项目 | C94: 中国市政工程华北设计研究总院有限公司 | D94: 2023.10.31 | E94: 171000 | H94: =E94-G94 -> 171000
A95: 23-HT-YY-094 | B95: 华腾供热2023-2024采暖水药剂采购项目 | C95: 功成（天津）锅炉技术有限公司 | D95: 2023.11.28 | E95: 无明细 | H95: 无明细 | I95: 单价：缓蚀阻垢剂22000/元 臭味剂 16800/元 缓蚀色精 169000/元 工业盐1450/元
A96: 23-HT-YY-095 | B96: 万新村供热站一网二级泵系统改造工程 | C96: 天津市政工程设计研究总院有限公司 | D96: 2023.11.5 | E96: 188000 | H96: =E96-G96 -> 188000
A97: 23-HT-YY-096 | B97: 华腾防汛物资采购项目 | C97: 天津普达瑞克机电工程有限公司 | D97: 2023.9.15 | E97: 54480 | G97: 54480 | H97: =E97-G97 -> 0
A98: 23-HT-YY-097 | B98: 2023年中山门地热舒畅嘉园夏季检修项目 | C98: 天津军星管业集团建设工程有限公司 | D98: 2023.10.26 | E98: 182232 | F98: 182232 | H98: =F98-G98 -> 182232
A99: 23-HT-YY-098 | B99: 2023-2024年华腾供热采暖季应急用工项目 | C99: 天津诚泓建筑工程有限公司 | D99: 2023.9.30 | E99: 312.6元/天 | F99: 182245.8 | G99: =140000+42245.8 -> 182245.8 | H99: =F99-G99 -> 0
H100: =SUM(H2:H99) -> 27383363

Sheet 华腾2021-2023汇总
A1: 华腾供热2021-2023年工程欠款明细表
A2: 序号 | B2: 工程地点及内容 | C2: 单位名称 | D2: 合同额 | E2: 结算值 | F2: 已付款 | G2: 欠付款 | H2: 备注
A3: 2021 | B3: 三东小区冬季抢修 | C3: 天津天铖力帆建筑工程有限公司 | D3: =华腾2021!E2 -> 25864 | E3: =华腾2021!F2 -> 25864 | F3: =华腾2021!G2 -> 25864 | G3: =E3-F3 -> 0
A4: 2021 | B4: 和平村站内检修 | C4: 天津永强东成市政工程有限公司 | D4: =华腾2021!E3 -> 87020 | E4: =华腾2021!F3 -> 87020 | F4: =华腾2021!G3 -> 87020 | G4: =E4-F4 -> 0
A5: 2021 | B5: 东城家园冬季检修 | C5: 天津永强东成市政工程有限公司 | D5: =华腾2021!E4 -> 46176 | E5: =华腾2021!F4 -> 46176 | F5: =华腾2021!G4 -> 46176 | G5: =E5-F5 -> 0
A6: 2021 | B6: 冬季内网抢修 | C6: 禹王（北京）科技工程有限公司 | D6: =华腾2021!E5 -> 255735 | E6: =华腾2021!F5 -> 255735 | F6: =华腾2021!G5 -> 255735 | G6: =E6-F6 -> 0
A7: 2021 | B7: 百合春天 九号站冬季抢修 | C7: 天津恒鼎建筑工程有限公司 | D7: =华腾2021!E6 -> 361256 | E7: =华腾2021!F6 -> 361256 | F7: =华腾2021!G6 -> 361256 | G7: =E7-F7 -> 0
A8: 2021 | B8: 万新供热2020-2021冬季运行供热管网抢修 | C8: 河北省广平县建筑安装企业集团公司 | D8: =华腾2021!E7 -> 136139 | E8: =华腾2021!F7 -> 136139 | F8: =华腾2021!G7 -> 136139 | G8: =E8-F8 -> 0
A9: 2021 | B9: 海河华馨冬季抢修 | C9: 天津市信恒建筑工程有限公司 | D9: =华腾2021!E8 -> 196770 | E9: =华腾2021!F8 -> 196770 | F9: =华腾2021!G8 -> 196770 | G9: =E9-F9 -> 0
A10: 2021 | B10: 团结北里秋丽家园冬季抢修 | C10: 天津军星管业集团建设工程有限公司 | D10: =华腾2021!E9 -> 29070 | E10: =华腾2021!F9 -> 29070 | F10: =华腾2021!G9 -> 29070 | G10: =E10-F10 -> 0
A11: 2021 | B11: 嘉华翠海朱庄子一村冬季抢修 | C11: 隽融建工（集团）有限公司 | D11: =华腾2021!E10 -> 90133 | E11: =华腾2021!F10 -> 90133 | F11: =华腾2021!G10 -> 90133 | G11: =E11-F11 -> 0
A12: 2021 | B12: 6号站万新公寓冬季抢修 | C12: 天津市翔凯建筑安装工程有限公司 | D12: =华腾2021!E11 -> 55095 | E12: =华腾2021!F11 -> 55095 | F12: =华腾2021!G11 -> 55095 | G12: =E12-F12 -> 0
A13: 2021 | B13: 2021年万新村1#2#3#换热站屋顶修缮工程 | C13: 天津大鼎市政工程有限公司 | D13: =华腾2021!E12 -> 179970 | E13: =华腾2021!F12 -> 172346 | F13: =华腾2021!G12 -> 172346 | G13: =E13-F13 -> 0 | H13: 郭天刚 18649222399
A14: 2021 | B14: 2021年万新村7#8#9#换热站屋顶修缮工程 | C14: 天津大鼎市政工程有限公司 | D14: =华腾2021!E13 -> 167424 | E14: =华腾2021!F13 -> 160232 | F14: =华腾2021!G13 -> 160232 | G14: =E14-F14 -> 0 | H14: 郭天刚 18649222399
A15: 2021 | B15: 2021年倚虹里1#-5#楼管道保温修缮工程 | C15: 天津大鼎市政工程有限公司 | D15: =华腾2021!E14 -> 163218 | E15: =华腾2021!F14 -> 161004 | F15: =华腾2021!G14 -> 161004 | G15: =E15-F15 -> 0 | H15: 郭天刚 18649222399
A16: 2021 | B16: 2021年松风西里1#-6#楼管道保温修缮工程 | C16: 天津大鼎市政工程有限公司 | D16: =华腾2021!E15 -> 184255 | E16: =华腾2021!F15 -> 177994 | F16: =华腾2021!G15 -> 177994 | G16: =E16-F16 -> 0 | H16: 郭天刚 18649222399
A17: 2021 | B17: 2021年一村换热站屋顶修缮工程 | C17: 天津大鼎市政工程有限公司 | D17: =华腾2021!E16 -> 161021 | E17: =华腾2021!F16 -> 153831 | F17: =华腾2021!G16 -> 153831 | G17: =E17-F17 -> 0 | H17: 郭天刚 18649222399
A18: 2021 | B18: 2021年和平村锅炉房手动葫芦改造工程 | C18: 天津大鼎市政工程有限公司 | D18: =华腾2021!E17 -> 124818 | E18: =华腾2021!F17 -> 115036 | F18: =华腾2021!G17 -> 115036 | G18: =E18-F18 -> 0 | H18: 郭天刚 18649222399
A19: 2021 | B19: 2021年倚虹中里1#-8#楼管道保温修缮工程 | C19: 天津大鼎市政工程有限公司 | D19: =华腾2021!E18 -> 173010 | E19: =华腾2021!F18 -> 169972 | F19: =华腾2021!G18 -> 169972 | G19: =E19-F19 -> 0 | H19: 郭天刚 18649222399
A20: 2021 | B20: 2021年倚虹东里1#-5#楼管道保温修缮工程 | C20: 天津大鼎市政工程有限公司 | D20: =华腾2021!E19 -> 159886 | E20: =华腾2021!F19 -> 158558 | F20: =华腾2021!G19 -> 158558 | G20: =E20-F20 -> 0 | H20: 郭天刚 18649222399
A21: 2021 | B21: 2021年万新村锅炉手动葫芦改造工程 | C21: 天津大鼎市政工程有限公司 | D21: =华腾2021!E20 -> 110949 | E21: =华腾2021!F20 -> 102255 | F21: =华腾2021!G20 -> 102255 | G21: =E21-F21 -> 0 | H21: 郭天刚 18649222399
A22: 2021 | B22: 2021年松风东里1#-5#楼管道保温修缮工程 | C22: 天津大鼎市政工程有限公司 | D22: =华腾2021!E21 -> 167423 | E22: =华腾2021!F21 -> 160729 | F22: =华腾2021!G21 -> 160729 | G22: =E22-F22 -> 0 | H22: 郭天刚 18649222399
A23: 2021 | B23: 2021年香兰家园换热站屋顶修缮工程 | C23: 天津大鼎市政工程有限公司 | D23: =华腾2021!E22 -> 174126 | E23: =华腾2021!F22 -> 166648 | F23: =华腾2021!G22 -> 166648 | G23: =E23-F23 -> 0 | H23: 郭天刚 18649222399
A24: 2021 | B24: 2021年百合春天换热站屋顶修缮工程 | C24: 天津大鼎市政工程有限公司 | D24: =华腾2021!E23 -> 182801 | E24: =华腾2021!F23 -> 175177 | F24: =华腾2021!G23 -> 175177 | G24: =E24-F24 -> 0 | H24: 郭天刚 18649222399
... A30: 2021 | B30: 2021年天泉东里3#4#入口截门更换工程 | C30: 中舰建筑工程（天津）有限公司 | D30: =华腾2021!E29 -> 151117 | E30: =华腾2021!F29 -> 141768 | F30: =华腾2021!G29 -> 141768 | G30: =E30-F30 -> 0 | H30: 郭天刚 18649222399
A31: 2021 | B31: 2021年秀悦换热站变压器维修项目 | C31: 中舰建筑工程（天津）有限公司 | D31: =华腾2021!E30 -> 188800 | E31: =华腾2021!F30 -> 0 | F31: =华腾2021!G30 -> 188800 | G31: =D31-F31 -> 0 | H31: 郭天刚 18649222399
A32: 2021 | B32: 2021年天泉西里14#15#16#17#入口截门更换工程 | C32: 中舰建筑工程（天津）有限公司 | D32: =华腾2021!E31 -> 181657 | E32: =华腾2021!F31 -> 169831 | F32: =华腾2021!G31 -> 169831 | G32: =E32-F32 -> 0 | H32: 郭天刚 18649222399
A33: 2021 | B33: 2021年远翠东里15#-23#入口截门更换工程 | C33: 中舰建筑工程（天津）有限公司 | D33: =华腾2021!E32 -> 190750 | E33: =华腾2021!F32 -> 177941 | F33: =华腾2021!G32 -> 177941 | G33: =E33-F33 -> 0 | H33: 郭天刚 18649222399
A34: 2021 | B34: 2021年和平村供热站变压器维修项目 | C34: 中舰建筑工程（天津）有限公司 | D34: =华腾2021!E33 -> 152701 | E34: =华腾2021!F33 -> 0 | F34: =华腾2021!G33 -> 152701 | G34: =D34-F34 -> 0 | H34: 郭天刚 18649222399
A35: 2021 | B35: 2021年贵环换热站变压器维修项目 | C35: 中舰建筑工程（天津）有限公司 | D35: =华腾2021!E34 -> 133848 | E35: =华腾2021!F34 -> 0 | F35: =华腾2021!G34 -> 133848 | G35: =D35-F35 -> 0 | H35: 郭天刚 18649222399
A36: 2021 | B36: 2021年香兰嘉园换热站变压器维修项目 | C36: 中舰建筑工程（天津）有限公司 | D36: =华腾2021!E35 -> 136749 | E36: =华腾2021!F35 -> 0 | F36: =华腾2021!G35 -> 136749 | G36: =D36-F36 -> 0 | H36: 郭天刚 18649222399
A37: 2021 | B37: 2021华馨地热站变压器维修项目 | C37: 中舰建筑工程（天津）有限公司 | D37: =华腾2021!E36 -> 192817 | E37: =华腾2021!F36 -> 0 | F37: =华腾2021!G36 -> 192817 | G37: =D37-F37 -> 0 | H37: 郭天刚 18649222399
A38: 2021 | B38: 2021年东城家园及和平村夏季检修工程 | C38: 天津永强东成市政工程有限公司 | D38: =华腾2021!E37 -> 170458 | E38: =华腾2021!F37 -> 170458 | F38: =华腾2021!G37 -> 170458 | G38: =D38-F38 -> 0
A39: 2021 | B39: 华腾招标代理咨询费/华腾供热站入围项目邀请招标 | C39: 天津津建工程造价咨询有限公司 | D39: =华腾2021!E38 -> 1291000 | E39: =华腾2021!F38 -> 0 | F39: =华腾2021!G38 -> 694000 | G39: =D39-F39 -> 597000
A40: 2021 | B40: 华腾供热有限责任公司各换热站变速器检测校准项目 | C40: 天津天星科技发展有限公司 | D40: =华腾2021!E39 -> 194400 | E40: =华腾2021!F39 -> 0 | F40: =华腾2021!G39 -> 194400 | G40: =D40-F40 -> 0 | H40: 郭天刚 18649222399
A41: 2021 | B41: 华腾供热有限责任公司流量计维护保养项目 | C41: 中舰建筑工程（天津）有限公司 | D41: =华腾2021!E40 -> 198856 | E41: =华腾2021!F40 -> 0 | F41: =华腾2021!G40 -> 198856 | G41: =D41-F41 -> 0 | H41: 郭天刚 18649222399
A42: 2021 | B42: 华腾供热贵环站站内夏季零星检修工程 | C42: 河北省广平县建筑安装企业集团公司 | D42: =华腾2021!E41 -> 197813 | E42: =华腾2021!F41 -> 0 | F42: =华腾2021!G41 -> 47813 | G42: =D42-F42 -> 150000
A43: 2021 | B43: 华腾供热临月里夏季零星检修工程 | C43: 河北省广平县建筑安装企业集团公司 | D43: =华腾2021!E42 -> 199772 | E43: =华腾2021!F42 -> 0 | F43: =华腾2021!G42 -> 99772 | G43: =D43-F43 -> 100000
A44: 2021 | B44: 华腾供热昆仑里、昆华里、昆悦里夏季零星检修工程 | C44: 天津荣开建筑工程有限公司 | D44: =华腾2021!E43 -> 191849 | E44: =华腾2021!F43 -> 0 | F44: =华腾2021!G43 -> 41849 | G44: =D44-F44 -> 150000
A45: 2021 | B45: 华腾供热晟悦、品香、润风、润景外网漏水检修工程 | C45: 天津荣开建筑工程有限公司 | D45: =华腾2021!E44 -> 97929 | E45: =华腾2021!F44 -> 0 | F45: =华腾2021!G44 -> 97929 | G45: =D45-F45 -> 0
A46: 2021 | B46: 2021年华馨片区夏季维修工程 | C46: 天津市信恒建筑工程有限公司 | D46: =华腾2021!E45 -> 141372 | E46: =华腾2021!F45 -> 0 | F46: =华腾2021!G45 -> 141372 | G46: =D46-F46 -> 0
A47: 2021 | B47: 2021年海河片区夏季检修工程 | C47: 天津市信恒建筑工程有限公司 | D47: =华腾2021!E46 -> 88420 | E47: =华腾2021!F46 -> 0 | F47: =华腾2021!G46 -> 88420 | G47: =D47-F47 -> 0
A48: 2021 | B48: 2021万新村供热站燃气热水锅炉本体保养 | C48: 天津市辰雨达机电设备销售有限公司 | D48: =华腾2021!E47 -> 198000 | E48: =华腾2021!F47 -> 0 | F48: =华腾2021!G47 -> 198000 | G48: =D48-F48 -> 0
A49: 2021 | B49: 2021和平村供热站燃气热水锅炉本体和燃烧器维修保养 | C49: 天津市辰雨达机电设备销售有限公司 | D49: =华腾2021!E48 -> 40000 | E49: =华腾2021!F48 -> 0 | F49: =华腾2021!G48 -> 40000 | G49: =D49-F49 -> 0
A50: 2021 | B50: 2021年万新村供热站下属换热站水泵维修 | C50: 天津市西青区万润机电设备维修中心 | D50: =华腾2021!E49 -> 178000 | E50: =华腾2021!F49 -> 0 | F50: =华腾2021!G49 -> 178000 | G50: =D50-F50 -> 0
A51: 2021 | B51: 华腾地热站7月份备品备件采购项目 | C51: 天津市东丽区重信瑞能暖通设备维修中心 | D51: =华腾2021!E50 -> 116940 | E51: =华腾2021!F50 -> 0 | F51: =华腾2021!G50 -> 116940 | G51: =D51-F51 -> 0
A52: 2021 | B52: 华腾供热站7月份备品备件采购 | C52: 天津市东丽区重信瑞能暖通设备维修中心 | D52: =华腾2021!E51 -> 41211 | E52: =华腾2021!F51 -> 0 | F52: =华腾2021!G51 -> 41211 | G52: =D52-F52 -> 0
A53: 2021 | B53: 2021和平村供热站燃气热水锅炉辅机软水器及除氧设备配件材料采购 | C53: 天津奥德宝机电设备有限公司 | D53: =华腾2021!E52 -> 71600 | E53: =华腾2021!F52 -> 0 | F53: =华腾2021!G52 -> 71600 | G53: =D53-F53 -> 0
... A55: 2021 | B55: 2021年华腾供热站可燃气探头校准项目 | C55: 天津赛恩斯检测服务有限公司 | D55: =华腾2021!E54 -> 18020 | E55: =华腾2021!F54 -> 0 | F55: =华腾2021!G54 -> 18020 | G55: =D55-F55 -> 0
A56: 2021 | B56: 2021年品香苑地热站热泵机组维修保养项目 | C56: 中舰建筑工程（天津）有限公司 | D56: =华腾2021!E55 -> 176080 | E56: =华腾2021!F55 -> 0 | F56: =华腾2021!G55 -> 176080 | G56: =D56-F56 -> 0 | H56: 郭天刚 18649222399
A57: 2021 | B57: 2021年万新村供热站仪表拆除工程 | C57: 天津和亚建筑工程有限公司 | D57: =华腾2021!E56 -> 121926 | E57: =华腾2021!F56 -> 107720 | F57: =华腾2021!G56 -> 107720 | G57: =E57-F57 -> 0 | H57: 郭天刚 18649222399
A58: 2021 | B58: 华腾供热造价咨询服务项目 | C58: 天勤工程咨询有限公司天津分公司 | D58: =华腾2021!E57 -> 157500 | E58: =华腾2021!F57 -> 0 | F58: =华腾2021!G57 -> 157500 | G58: =D58-F58 -> 0
A59: 2021 | B59: 2021年和平村供热站仪表拆除工程 | C59: 天津和亚建筑工程有限公司 | D59: =华腾2021!E58 -> 13548 | E59: =华腾2021!F58 -> 11969 | F59: =华腾2021!G58 -> 11969 | G59: =E59-F59 -> 0 | H59: 郭天刚 18649222399
A60: 2021 | B60: 2021年秀悦园地热站热泵机组维修保养项目 | C60: 天津蒙兴建筑工程有限公司 | D60: =华腾2021!E59 -> 185310 | E60: =华腾2021!F59 -> 0 | F60: =华腾2021!G59 -> 185310 | G60: =D60-F60 -> 0 | H60: 郭天刚 18649222399
A61: 2021 | B61: 2021年万新村供热站锅炉燃烧器维保服务 | C61: 天津市北方建华机电设备有限公司 | D61: =华腾2021!E60 -> 198000 | E61: =华腾2021!F60 -> 0 | F61: =华腾2021!G60 -> 98000 | G61: =D61-F61 -> 100000
A62: 2021 | B62: 2021年万新村锅炉房40吨燃气锅炉内部清垢喷防腐涂料保养 | C62: 天津市敬启建筑工程有限公司 | D62: =华腾2021!E61 -> 79200 | E62: =华腾2021!F61 -> 0 | F62: =华腾2021!G61 -> 79200 | G62: =D62-F62 -> 0 | H62: 郭天刚 18649222399
A63: 2021 | B63: 2021年海河新天地地热泵机组维修保养项目 | C63: 天津市敬启建筑工程有限公司 | D63: =华腾2021!E62 -> 184870 | E63: =华腾2021!F62 -> 0 | F63: =华腾2021!G62 -> 184870 | G63: =D63-F63 -> 0 | H63: 郭天刚 18649222399
A64: 2021 | B64: 2021年东惠地热站热泵机组维修保养项目 | C64: 天津市敬启建筑工程有限公司 | D64: =华腾2021!E63 -> 194850 | E64: =华腾2021!F63 -> 0 | F64: =华腾2021!G63 -> 194850 | G64: =D64-F64 -> 0 | H64: 郭天刚 18649222399
A65: 2021 | B65: 2021年华馨地热站热泵机组维修保养 | C65: 天津市众致建筑工程有限公司 | D65: =华腾2021!E64 -> 150160 | E65: =华腾2021!F64 -> 0 | F65: =华腾2021!G64 -> 150160 | G65: =D65-F65 -> 0 | H65: 郭天刚 18649222399
A66: 2021 | B66: 2021年万新村锅炉房80吨燃气锅炉内部清垢喷防腐涂料保养 | C66: 天津市众致建筑工程有限公司 | D66: =华腾2021!E65 -> 158400 | E66: =华腾2021!F65 -> 0 | F66: =华腾2021!G65 -> 158400 | G66: =D66-F66 -> 0 | H66: 郭天刚 18649222399
A67: 2021 | B67: 2021年东瑞地热站热泵机组维修保养 | C67: 天津市众致建筑工程有限公司 | D67: =华腾2021!E66 -> 169260 | E67: =华腾2021!F66 -> 0 | F67: =华腾2021!G66 -> 169260 | G67: =D67-F67 -> 0 | H67: 郭天刚 18649222399
A68: 2021 | B68: 华腾供热站可燃气体检测 | C68: 天津荣开建筑工程有限公司 | D68: =华腾2021!E67 -> 40897 | E68: =华腾2021!F67 -> 36343 | F68: =华腾2021!G67 -> 36343 | G68: =E68-F68 -> 0
A69: 2021 | B69: 万新村供热站水泵保养 | C69: 天津市红桥区丰顺盈机电设备销售中心 | D69: =华腾2021!E68 -> 115000 | E69: =华腾2021!F68 -> 0 | F69: =华腾2021!G68 -> 115000 | G69: =D69-F69 -> 0
A70: 2021 | B70: 华腾供热公司消防物联网DN800管线设备采购 | C70: 中安昊天（北京）安全技术有限公司 | D70: =华腾2021!E69 -> 191535 | E70: =华腾2021!F69 -> 0 | F70: =华腾2021!G69 -> 191535 | G70: =D70-F70 -> 0
A71: 2021 | B71: 华腾供热智慧消防平台软件采购 | C71: 中安昊天（北京）安全技术有限公司 | D71: =华腾2021!E70 -> 36160 | E71: =华腾2021!F70 -> 0 | F71: =华腾2021!G70 -> 36160 | G71: =D71-F71 -> 0
A72: 2021 | B72: 华腾供热公司DN600、DN700管线设备采购 | C72: 北京星联众合科技有限公司 | D72: =华腾2021!E71 -> 164605 | E72: =华腾2021!F71 -> 0 | F72: =华腾2021!G71 -> 164605 | G72: =D72-F72 -> 0
A73: 2021 | B73: 华腾供热公司消防物联网DN800管线设备安装工程 | C73: 天津荣开建筑工程有限公司 | D73: =华腾2021!E72 -> 125844 | E73: =华腾2021!F72 -> 119391 | F73: =华腾2021!G72 -> 119391 | G73: =E73-F73 -> 0
A74: 2021 | B74: 和平村锅炉房燃气锅炉内部清垢喷防腐涂料保养 | C74: 天津市敬启建筑工程有限公司 | D74: =华腾2021!E73 -> 158400 | E74: =华腾2021!F73 -> 0 | F74: =华腾2021!G73 -> 158400 | G74: =D74-F74 -> 0 | H74: 郭天刚 18649222399
A75: 2021 | B75: 华腾供热站氮氧化物转换器采购 | C75: 天津仁和嘉境科技有限公司 | D75: =华腾2021!E74 -> 72000 | E75: =华腾2021!F74 -> 0 | F75: =华腾2021!G74 -> 72000 | G75: =D75-F75 -> 0
A76: 2021 | B76: 万新村供热站7号站2021年夏季维修工程 | C76: 天津恒鼎建筑工程有限公司 | D76: =华腾2021!E75 -> 155837 | E76: =华腾2021!F75 -> 168080 | F76: =华腾2021!G75 -> 168080 | G76: =华腾2021!H75 -> 0
A77: 2021 | B77: 万新村供热站8号站2021年夏季维修 | C77: 天津恒鼎建筑工程有限公司 | D77: =华腾2021!E76 -> 83995 | E77: =华腾2021!F76 -> 90762 | F77: =华腾2021!G76 -> 90762 | G77: =E77-F77 -> 0
A78: 2021 | B78: 万新村供热站9号站2021年夏季维修 | C78: 天津恒鼎建筑工程有限公司 | D78: =华腾2021!E77 -> 186730 | E78: =华腾2021!F77 -> 191479 | F78: =华腾2021!G77 -> 191479 | G78: =华腾2021!H77 -> 0
A79: 2021 | B79: 万新村供热站百合春天站2021年夏季维修 | C79: 中津鹏程（天津）建筑工程有限公司 | D79: =华腾2021!E78 -> 162442 | E79: =华腾2021!F78 -> 170089 | F79: =华腾2021!G78 -> 170089 | G79: =E79-F79 -> 0
A80: 2021 | B80: 万新村供热站9号站楼道立管、盘管维修 | C80: 中津鹏程（天津）建筑工程有限公司 | D80: =华腾2021!E79 -> 145494 | E80: =华腾2021!F79 -> 154171 | F80: =华腾2021!G79 -> 154171 | G80: =华腾2021!H79 -> 0
A81: 2021 | B81: 2021年朱庄子站检修工程 | C81: 隽融建工（集团）有限公司 | D81: =华腾2021!E80 -> 179385 | E81: =华腾2021!F80 -> 179385 | F81: =华腾2021!G80 -> 179385 | G81: =D81-F81 -> 0
A82: 2021 | B82: 2021年汉拿站检修工程 | C82: 隽融建工（集团）有限公司 | D82: =华腾2021!E81 -> 173698 | E82: =华腾2021!F81 -> 0 | F82: =华腾2021!G81 -> 173698 | G82: =D82-F82 -> 0
A83: 2021 | B83: 2021年一村站检修工程 | C83: 隽融建工（集团）有限公司 | D83: =华腾2021!E82 -> 190315 | E83: =华腾2021!F82 -> 0 | F83: =华腾2021!G82 -> 190315 | G83: =D83-F83 -> 0
A84: 2021 | B84: 2021年嘉华站检修工程 | C84: 隽融建工（集团）有限公司 | D84: =华腾2021!E83 -> 160703 | E84: =华腾2021!F83 -> 160703 | F84: =华腾2021!G83 -> 160703 | G84: =D84-F84 -> 0
A85: 2021 | B85: 2021华腾供热电磁阀维修保养项目 | C85: 天津蒙兴建筑工程有限公司 | D85: =华腾2021!E84 -> 115154 | E85: =华腾2021!F84 -> 0 | F85: =华腾2021!G84 -> 115154 | G85: =D85-F85 -> 0 | H85: 郭天刚 18649222399
A86: 2021 | B86: 2021年万新村供热站屋面维修工程 | C86: 天津荣开建筑工程有限公司 | D86: =华腾2021!E85 -> 126748 | E86: =华腾2021!F85 -> 121550 | F86: =华腾2021!G85 -> 121550 | G86: =E86-F86 -> 0
A87: 2021 | B87: 2021年万新村锅炉房锅炉保养防腐涂料采购项目 | C87: 廊坊一萍锅炉保养工程有限公司 | D87: =华腾2021!E86 -> 197500 | E87: =华腾2021!F86 -> 0 | F87: =华腾2021!G86 -> 197500 | G87: =D87-F87 -> 0
A88: 2021 | B88: 2021年万新村供热截堵恢复材料采购 | C88: 天津市东丽区重信瑞能暖通设备维修中心 | D88: =华腾2021!E87 -> 37515.6 | E88: =华腾2021!F87 -> 0 | F88: =华腾2021!G87 -> 37515.6 | G88: =D88-F88 -> 0
A89: 2021 | B89: 2021万新村锅炉房锅炉防腐保养采购 | C89: 天津大展锅炉技术有限公司 | D89: =华腾2021!E88 -> 198500 | E89: =华腾2021!F88 -> 0 | F89: =华腾2021!G88 -> 198500 | G89: =D89-F89 -> 0
A90: 2021 | B90: 2021万新村换热站板式换热器清洗项目 | C90: 天津大展锅炉技术有限公司 | D90: =华腾2021!E89 -> 按55/平米 | E90: =华腾2021!F89 -> 339429.75 | F90: =华腾2021!G89 -> 0 | G90: =E90-F90 -> 339429.75
A91: 2021 | B91: 2021万新村供热站下属369片区备品备件采购 | C91: 天津市晋之鑫五金经销部 | D91: =华腾2021!E90 -> 48460 | E91: =华腾2021!F90 -> 0 | F91: =华腾2021!G90 -> 48460 | G91: =D91-F91 -> 0
A92: 2021 | B92: 万新村供热站2021年7月份备品备件采购 | C92: 天津市津南区明悦五金经营部 | D92: =华腾2021!E91 -> 48222 | E92: =华腾2021!F91 -> 0 | F92: =华腾2021!G91 -> 48222 | G92: =D92-F92 -> 0
A93: 2021 | B93: 2021贵环站、3号站、百合站、9号站换热站等8月份备品备件采购 | C93: 天津市东丽区环昆达五金经营部 | D93: =华腾2021!E92 -> 156816.8 | E93: =华腾2021!F92 -> 0 | F93: =华腾2021!G92 -> 156816.8 | G93: =D93-F93 -> 0
A94: 2021 | B94: 2021年一村站、东城站、好美站换热站等8月份备品备件采购 | C94: 天津市东丽区华达龙阀门销售部 | D94: =华腾2021!E93 -> 179535.1 | E94: =华腾2021!F93 -> 0 | F94: =华腾2021!G93 -> 179535.1 | G94: =D94-F94 -> 0
A95: 2021 | B95: 2021年秋丽园北换热站离心泵采购 | C95: 天津市无双众鑫科技发展有限公司 | D95: =华腾2021!E94 -> 88340 | E95: =华腾2021!F94 -> 0 | F95: =华腾2021!G94 -> 88340 | G95: =D95-F95 -> 0
A96: 2021 | B96: 万新村三号管理站和海山北里片区2021夏季维修工程 | C96: 禹王（北京）科技工程有限公司 | D96: =华腾2021!E95 -> 113714 | E96: =华腾2021!F95 -> 113714 | F96: =华腾2021!G95 -> 113714 | G96: =D96-F96 -> 0
A97: 2021 | B97: 2021万新村供热站烟气在线监测CEMS系统维修服务 | C97: 天津市敬启建筑工程有限公司 | D97: =华腾2021!E96 -> 172840 | E97: =华腾2021!F96 -> 0 | F97: =华腾2021!G96 -> 172840 | G97: =D97-F97 -> 0 | H97: 郭天刚 18649222399
A98: 2021 | B98: 2021华腾万新村东城片区更换球阀采购 | C98: 天津市东丽区重信瑞能暖通设备维修中心 | D98: =华腾2021!E97 -> 36250 | E98: =华腾2021!F97 -> 0 | F98: =华腾2021!G97 -> 36250 | G98: =D98-F98 -> 0
A99: 2021 | B99: 2021泰通公寓、百合春天更换阀门 | C99: 天津市东丽区重信瑞能暖通设备维修中心 | D99: =华腾2021!E98 -> 10156 | E99: =华腾2021!F98 -> 0 | F99: =华腾2021!G98 -> 10156 | G99: =D99-F99 -> 0
A100: 2021 | B100: 2021贵环小区、卫国道十六局、机扫队、海河新天地等换热站电气材料采购 | C100: 天津鼎邦电气有限公司 | D100: =华腾2021!E99 -> 194070 | E100: =华腾2021!F99 -> 0 | F100: =华腾2021!G99 -> 194070 | G100: =D100-F100 -> 0
A101: 2021 | B101: 2021东惠换热站电气采购 | C101: 天津鼎邦电气有限公司 | D101: =华腾2021!E100 -> 188980 | E101: =华腾2021!F100 -> 0 | F101: =华腾2021!G100 -> 188980 | G101: =D101-F101 -> 0
A102: 2021 | B102: 2021东瑞换热站电气采购 | C102: 天津鼎邦电气有限公司 | D102: =华腾2021!E101 -> 198200 | E102: =华腾2021!F101 -> 0 | F102: =华腾2021!G101 -> 198200 | G102: =D102-F102 -> 0
A103: 2021 | B103: 2021万新村四五六号站维修材料采购 | C103: 天津市东丽区重信瑞能暖通设备维修中心 | D103: =华腾2021!E102 -> 49720 | E103: =华腾2021!F102 -> 0 | F103: =华腾2021!G102 -> 49720 | G103: =D103-F103 -> 0
A104: 2021 | B104: 2021东康A站电磁流量计采购 | C104: 天津亚华仪科技有限公司 | D104: =华腾2021!E103 -> 42200 | E104: =华腾2021!F103 -> 0 | F104: =华腾2021!G103 -> 42200 | G104: =D104-F104 -> 0
A105: 2021 | B105: 2021年中山门、秋丽家园夏季检修 | C105: 天津军星管业集团建设工程有限公司 | D105: =华腾2021!E104 -> 121197 | E105: =华腾2021!F104 -> 121197 | F105: =华腾2021!G104 -> 121197 | G105: =D105-F105 -> 0
A106: 2021 | B106: 2021华腾地热站维修材料采购 | C106: 天津市东丽区丰凯捷建材经营部 | D106: =华腾2021!E105 -> 102917 | E106: =华腾2021!F105 -> 0 | F106: =华腾2021!G105 -> 102917 | G106: =D106-F106 -> 0
...
